{"status":"ok","cached":false,"companyTotal":{"sales":367851.1299999999,"plan":1091990,"gp":156377.56039999984,"gpPct":42.51109963968302,"txns":10533,"customers":9572,"storeCount":132,"pctToPlan":33.6863093984377},"topStores":[{"store":"209","name":"MOUNT JOY, PA - ACE","city":"Mount Joy","state":"PA","sales":11398.85,"plan":32418.22,"pctToPlan":35.16186268092449,"gp":4495.6079,"gpPct":39.43913552682946,"txns":228,"customers":212},{"store":"192","name":"BEVERLY, MA - ACE","city":"Beverly","state":"MA","sales":10350.22,"plan":25894.6,"pctToPlan":39.97057301522325,"gp":4134.980299999999,"gpPct":39.95065129050396,"txns":213,"customers":198},{"store":"210","name":"QUINCY, MA - ACE","city":"Quincy","state":"MA","sales":8440.25,"plan":24257.99,"pctToPlan":34.793690656150815,"gp":3132.8116,"gpPct":37.11752140043245,"txns":145,"customers":134},{"store":"217","name":"NORTH SPRINGFIELD, VT - ACE","city":"North Springfield","state":"VT","sales":7511.6,"plan":20411.21,"pctToPlan":36.801345927066556,"gp":2981.1008,"gpPct":39.68662868097343,"txns":155,"customers":141},{"store":"6","name":"MOULTONBORO, NH - (IND)","city":"Moultonboro","state":"NH","sales":7021.97,"plan":12732.58,"pctToPlan":55.14962403534869,"gp":2682.1986000000006,"gpPct":38.197238097001275,"txns":120,"customers":115},{"store":"172","name":"FALMOUTH, MA - (IND)","city":"Teaticket","state":"MA","sales":6738,"plan":17603.09,"pctToPlan":38.277370620726245,"gp":2807.4987,"gpPct":41.66664737310774,"txns":178,"customers":164},{"store":"171","name":"BELFAST, ME - ACE","city":"Belfast","state":"ME","sales":6572.61,"plan":11676.18,"pctToPlan":56.29075605206497,"gp":2397.3899999999994,"gpPct":36.47546408504383,"txns":133,"customers":118},{"store":"182","name":"COHASSET, MA - (IND)","city":"Cohasset","state":"MA","sales":6276.17,"plan":11568.15,"pctToPlan":54.25387810496925,"gp":2403.0276,"gpPct":38.288121577331395,"txns":125,"customers":113},{"store":"236","name":"DOVER, PA - ACE","city":"Dover","state":"PA","sales":6005.87,"plan":23048.07,"pctToPlan":26.058017005328427,"gp":2526.0733,"gpPct":42.060072895350714,"txns":168,"customers":158},{"store":"167","name":"ALTON, NH - ACE","city":"Alton","state":"NH","sales":5885.71,"plan":8398.59,"pctToPlan":70.07973957533348,"gp":2472.812,"gpPct":42.01382670909712,"txns":88,"customers":81},{"store":"4","name":"GARDNER, MA - ACE","city":"Gardner","state":"MA","sales":5309.55,"plan":10460.88,"pctToPlan":50.75624612843279,"gp":2252.48,"gpPct":42.423180872201975,"txns":130,"customers":123},{"store":"198","name":"LYNDONVILLE, VT - ACE","city":"Lyndonville","state":"VT","sales":5085.48,"plan":15791.27,"pctToPlan":32.204376215465885,"gp":1900.0297999999993,"gpPct":37.361857681084174,"txns":118,"customers":108},{"store":"74","name":"EASTHAMPTON, MA - ACE","city":"Easthampton","state":"MA","sales":4948.94,"plan":8300.79,"pctToPlan":59.6201084475092,"gp":2132.4351999999994,"gpPct":43.0887260706333,"txns":128,"customers":119},{"store":"153","name":"KINGSTON, MA - ACE","city":"Kingston","state":"MA","sales":4691.67,"plan":15310.01,"pctToPlan":30.644460715571054,"gp":1942.5468,"gpPct":41.40416525458952,"txns":109,"customers":102},{"store":"63","name":"MIDDLEBURY, VT - ACE","city":"Middlebury","state":"VT","sales":4600.17,"plan":10534.68,"pctToPlan":43.66691726753921,"gp":1831.3184,"gpPct":39.809798333539845,"txns":124,"customers":114},{"store":"49","name":"BARRE, VT - IND","city":"Barre","state":"VT","sales":4435.33,"plan":12568.47,"pctToPlan":35.28933911605788,"gp":2011.2628999999997,"gpPct":45.34640939907515,"txns":96,"customers":87},{"store":"219","name":"WOODSTOCK, VT - ACE","city":"Woodstock","state":"VT","sales":4283.86,"plan":8754.87,"pctToPlan":48.93116631086469,"gp":1960.4031999999997,"gpPct":45.76254125951828,"txns":104,"customers":97},{"store":"16","name":"NORWAY, ME - ACE","city":"Norway","state":"ME","sales":4037.04,"plan":7363.43,"pctToPlan":54.825536468738065,"gp":1526.1547,"gpPct":37.80380427243723,"txns":111,"customers":91},{"store":"158","name":"POCASSET, MA - ACE","city":"Pocasset","state":"MA","sales":3976.4,"plan":7980.15,"pctToPlan":49.828637306316296,"gp":1362.098,"gpPct":34.254551855950105,"txns":86,"customers":78},{"store":"118","name":"GREENFIELD, MA - (IND)","city":"Greenfield","state":"MA","sales":3876.07,"plan":7510.64,"pctToPlan":51.60771918238659,"gp":1453.1062000000002,"gpPct":37.489162992412425,"txns":101,"customers":89},{"store":"202","name":"EASTCHESTER, NY - (ACE)","city":"Eastchester","state":"NY","sales":3852.75,"plan":14739.79,"pctToPlan":26.138432094351412,"gp":1951.962,"gpPct":50.66412302900526,"txns":150,"customers":142},{"store":"113","name":"TUPPER LAKE, NY - ACE","city":"Tupper Lake","state":"NY","sales":3744.61,"plan":9241.91,"pctToPlan":40.51770683765585,"gp":1538.7627000000002,"gpPct":41.09273595915196,"txns":77,"customers":67},{"store":"203","name":"BRISTOL, VT - (ACE)","city":"Bristol","state":"VT","sales":3671.11,"plan":8177.55,"pctToPlan":44.89254116452972,"gp":1493.21,"gpPct":40.674618848250255,"txns":97,"customers":90},{"store":"206","name":"WINSLOW, ME - ACE","city":"Winslow","state":"ME","sales":3598.96,"plan":7326.88,"pctToPlan":49.11995283121875,"gp":1195.0092,"gpPct":33.204292351123655,"txns":96,"customers":91},{"store":"204","name":"MADISON, ME - ACE","city":"Madison","state":"ME","sales":3591.58,"plan":5209.61,"pctToPlan":68.94143707494419,"gp":890.3510999999999,"gpPct":24.789955952533422,"txns":71,"customers":68},{"store":"156","name":"SO. SANDWICH, MA - (IND)","city":"Sandwich","state":"MA","sales":3589.58,"plan":8916.4,"pctToPlan":40.25817594544884,"gp":1537.4038,"gpPct":42.829629093097246,"txns":82,"customers":75},{"store":"220","name":"PENNSBURG, PA - ACE","city":"Pennsburg","state":"PA","sales":3585.42,"plan":13154.11,"pctToPlan":27.257032212745674,"gp":1637.508,"gpPct":45.67130210686614,"txns":104,"customers":96},{"store":"213","name":"BRATTLEBORO, VT - ACE","city":"Brattleboro","state":"VT","sales":3576.53,"plan":9480.4,"pctToPlan":37.72551791063668,"gp":1704.4949000000001,"gpPct":47.6577828230156,"txns":122,"customers":107},{"store":"207","name":"FARMINGDALE, ME - ACE","city":"Farmingdale","state":"ME","sales":3540.1,"plan":5882.4,"pctToPlan":60.1812185502516,"gp":1587.8398,"gpPct":44.85296460551962,"txns":82,"customers":76},{"store":"190","name":"IPSWICH, MA - ACE","city":"Ipswich","state":"MA","sales":3513.71,"plan":10408.45,"pctToPlan":33.75824450326417,"gp":1367.9993,"gpPct":38.933187428672255,"txns":95,"customers":87},{"store":"211","name":"HANOVER, MA - ACE","city":"Hanover","state":"MA","sales":3457.6,"plan":10203.93,"pctToPlan":33.884983530855266,"gp":1439.3663999999999,"gpPct":41.629060620083294,"txns":82,"customers":70},{"store":"144","name":"HAVERHILL, MA - ACE","city":"Haverhill","state":"MA","sales":3434.9,"plan":7201.53,"pctToPlan":47.696808872559025,"gp":1583.4895000000001,"gpPct":46.10001746775743,"txns":86,"customers":72},{"store":"231","name":"WATERTOWN, CT - ACE","city":"Watertown","state":"CT","sales":3345.06,"plan":11569.68,"pctToPlan":28.912294894932273,"gp":1628.8177,"gpPct":48.6932282231111,"txns":96,"customers":90},{"store":"178","name":"DOVER, NH - IND","city":"Dover","state":"NH","sales":3330.62,"plan":5922.46,"pctToPlan":56.23710417630512,"gp":1255.6751999999997,"gpPct":37.70094456887906,"txns":72,"customers":64},{"store":"226","name":"COBLESKILL, NY - ACE","city":"Cobleskill","state":"NY","sales":3317.65,"plan":7405.05,"pctToPlan":44.802533406256536,"gp":1367.7137,"gpPct":41.22537639594291,"txns":87,"customers":80},{"store":"45","name":"MONTPELIER, VT - ACE","city":"Montpelier","state":"VT","sales":3315.99,"plan":8972.59,"pctToPlan":36.956887587641916,"gp":1448.7413999999999,"gpPct":43.6895587743027,"txns":115,"customers":108},{"store":"183","name":"HINESBURG, VT - ACE","city":"Hinesburg","state":"VT","sales":3309.25,"plan":7338.21,"pctToPlan":45.096147425598346,"gp":1522.9643,"gpPct":46.02143385963588,"txns":89,"customers":79},{"store":"218","name":"SOUTH BURLINGTON, VT - ACE","city":"South Burlington","state":"VT","sales":3282.82,"plan":9231.16,"pctToPlan":35.56237785933729,"gp":1463.7045,"gpPct":44.5868034190117,"txns":107,"customers":101},{"store":"90","name":"WELLS, ME - (ACE)","city":"Wells","state":"ME","sales":3252.31,"plan":8655.22,"pctToPlan":37.57628344513485,"gp":1462.596,"gpPct":44.970989850291026,"txns":105,"customers":101},{"store":"212","name":"BRUNSWICK, MD - ACE","city":"Brunswick","state":"MD","sales":3250.27,"plan":10705.59,"pctToPlan":30.360493910190844,"gp":1176.1334000000002,"gpPct":36.18571380223797,"txns":82,"customers":77},{"store":"32","name":"FRANKLIN, MA - ACE","city":"Franklin","state":"MA","sales":3238.6,"plan":7653.02,"pctToPlan":42.317934619274475,"gp":1350.2626,"gpPct":41.69278700673131,"txns":98,"customers":85},{"store":"22","name":"LINCOLN, NH - ACE","city":"Lincoln","state":"NH","sales":3222.02,"plan":6518.08,"pctToPlan":49.432041337326325,"gp":1301.753,"gpPct":40.4017665936276,"txns":73,"customers":66},{"store":"215","name":"COLCHESTER, VT - ACE","city":"Colchester","state":"VT","sales":3208.31,"plan":9245.42,"pctToPlan":34.701614420978174,"gp":1387.3824,"gpPct":43.24340228967899,"txns":100,"customers":86},{"store":"136","name":"LAKE PLACID, NY - ACE","city":"Lake Placid","state":"NY","sales":3155.38,"plan":8182.36,"pctToPlan":38.56320181463539,"gp":1270.2658000000001,"gpPct":40.257141770563294,"txns":96,"customers":83},{"store":"25","name":"SAINT JOHNSBURY, VT - ACE","city":"Saint Johnsbury","state":"VT","sales":3062.6,"plan":7609.71,"pctToPlan":40.245948925780354,"gp":1410.5538999999999,"gpPct":46.05739894207536,"txns":86,"customers":78},{"store":"8","name":"CLINTON, MA - ACE","city":"Clinton","state":"MA","sales":3027.73,"plan":6250.18,"pctToPlan":48.44228486219597,"gp":1381.7609,"gpPct":45.63685995779016,"txns":83,"customers":79},{"store":"227","name":"RUTLAND, VT - ACE","city":"Rutland","state":"VT","sales":3010.9,"plan":8175.53,"pctToPlan":36.82819340152871,"gp":1503.621,"gpPct":49.93925404364144,"txns":99,"customers":85},{"store":"224","name":"VILLAS, NJ - ACE","city":"Villas","state":"NJ","sales":3002.74,"plan":10848.35,"pctToPlan":27.679232325653206,"gp":1554.0985999999998,"gpPct":51.756016171896334,"txns":113,"customers":102},{"store":"175","name":"LEE, NH - ACE","city":"Lee","state":"NH","sales":2955.29,"plan":11944.75,"pctToPlan":24.741329872956737,"gp":1273.1304,"gpPct":43.07971129736845,"txns":94,"customers":87},{"store":"237","name":"CUMBERLAND, RI - ACE","city":"Cumberland","state":"RI","sales":2926.99,"plan":7950.14,"pctToPlan":36.816835929933305,"gp":1273.8008999999997,"gpPct":43.51914082384975,"txns":112,"customers":95},{"store":"56","name":"OLD TOWN, ME - ACE","city":"Old Town","state":"ME","sales":2884.36,"plan":5551.22,"pctToPlan":51.95902882609589,"gp":1191.5475000000001,"gpPct":41.31063736842835,"txns":91,"customers":82},{"store":"230","name":"WOODBURY,  CT - ACE","city":"Woodbury","state":"CT","sales":2875.57,"plan":12792.74,"pctToPlan":22.478139945000056,"gp":1183.3785000000003,"gpPct":41.15283230802937,"txns":87,"customers":80},{"store":"201","name":"SOUTH ROYALTON, VT - ACE","city":"South Royalton","state":"VT","sales":2867.38,"plan":7990.65,"pctToPlan":35.884189646649524,"gp":1267.3454000000002,"gpPct":44.19872496843809,"txns":89,"customers":81},{"store":"3","name":"MEREDITH, NH - (IND)","city":"Meredith","state":"NH","sales":2741.57,"plan":7552.37,"pctToPlan":36.300790347930516,"gp":1084.9734,"gpPct":39.57489321811954,"txns":69,"customers":63},{"store":"151","name":"MIDDLEBORO, MA - ACE","city":"Middleboro","state":"MA","sales":2708.12,"plan":6704.92,"pctToPlan":40.390041939351995,"gp":909.471,"gpPct":33.58311300828619,"txns":74,"customers":66},{"store":"42","name":"LUDLOW, VT - ACE","city":"Ludlow","state":"VT","sales":2694.94,"plan":6864.76,"pctToPlan":39.25759968301878,"gp":1008.0373,"gpPct":37.40481420736639,"txns":54,"customers":51},{"store":"37","name":"WEBSTER, MA - (ACE)","city":"Webster","state":"MA","sales":2662.77,"plan":7213.97,"pctToPlan":36.911298494448964,"gp":1066.8665,"gpPct":40.06604025131724,"txns":70,"customers":64},{"store":"135","name":"NAPLES, ME - ACE","city":"Naples","state":"ME","sales":2635.07,"plan":6998.43,"pctToPlan":37.65230201630938,"gp":1334.1376000000002,"gpPct":50.630062958479286,"txns":92,"customers":80},{"store":"214","name":"BURLINGTON, VT - ACE","city":"Burlington","state":"VT","sales":2632.45,"plan":7281.04,"pctToPlan":36.154862492171446,"gp":1162.4252999999999,"gpPct":44.157545252521416,"txns":98,"customers":88},{"store":"152","name":"CARVER, MA - ACE","city":"Carver","state":"MA","sales":2632.04,"plan":5932.28,"pctToPlan":44.36810130337746,"gp":1202.9669999999999,"gpPct":45.704738529809575,"txns":83,"customers":79},{"store":"132","name":"EASTON, NY - ACE","city":"Greenwich","state":"NY","sales":2605.51,"plan":8018.82,"pctToPlan":32.49243654303252,"gp":1198.409,"gpPct":45.995179446634246,"txns":79,"customers":70},{"store":"161","name":"JEFFERSONVILLE, VT - (ACE)","city":"Jeffersonville","state":"VT","sales":2602.52,"plan":5272.02,"pctToPlan":49.364759617755624,"gp":1234.079,"gpPct":47.418617340116505,"txns":66,"customers":61},{"store":"205","name":"SKOWHEGAN, ME - ACE","city":"Skowhegan","state":"ME","sales":2596.87,"plan":6855.02,"pctToPlan":37.882748700952,"gp":1246.9696999999999,"gpPct":48.01817957772241,"txns":86,"customers":81},{"store":"221","name":"PHOENIXVILLE, PA - ACE","city":"Phoenixville","state":"PA","sales":2560.08,"plan":11616.08,"pctToPlan":22.039104413881446,"gp":1107.7055,"gpPct":43.268393956438864,"txns":96,"customers":84},{"store":"188","name":"STOW, MA - IND","city":"Stow","state":"MA","sales":2461.09,"plan":6608.27,"pctToPlan":37.242576347516064,"gp":1105.1438,"gpPct":44.90464794054667,"txns":69,"customers":63},{"store":"124","name":"NEWPORT, ME - ACE","city":"Newport","state":"ME","sales":2439.62,"plan":5929.6,"pctToPlan":41.143078791149485,"gp":1166.5779,"gpPct":47.81801674031202,"txns":96,"customers":89},{"store":"108","name":"FARMINGTON, ME - ACE","city":"Farmington","state":"ME","sales":2436.51,"plan":5511.94,"pctToPlan":44.20421847843047,"gp":1145.2317000000003,"gpPct":47.0029550463573,"txns":67,"customers":62},{"store":"200","name":"NEW HOPE, PA - ACE","city":"New Hope","state":"PA","sales":2361.78,"plan":7061.6,"pctToPlan":33.44539481137419,"gp":1215.0865000000001,"gpPct":51.44791216794113,"txns":100,"customers":87},{"store":"189","name":"OSSIPEE, NH - (ACE)","city":"Center Ossipee","state":"NH","sales":2321.64,"plan":5893.51,"pctToPlan":39.39316298776111,"gp":1157.2912999999999,"gpPct":49.84800830447442,"txns":82,"customers":76},{"store":"7","name":"TEWKSBURY, MA - (IND)","city":"Tewksbury","state":"MA","sales":2299.02,"plan":7647.74,"pctToPlan":30.061429912627784,"gp":1079.2477,"gpPct":46.94381519082043,"txns":74,"customers":67},{"store":"94","name":"WILLIAMSTOWN, MA - ACE","city":"Williamstown","state":"MA","sales":2273.01,"plan":7316.78,"pctToPlan":31.065714699635638,"gp":972.2111000000002,"gpPct":42.77196756723464,"txns":70,"customers":64},{"store":"65","name":"LITTLETON, MA - (IND)","city":"Littleton","state":"MA","sales":2271.23,"plan":8156.58,"pctToPlan":27.84537146696287,"gp":991.5935999999999,"gpPct":43.658880870717624,"txns":42,"customers":37},{"store":"57","name":"MORRISVILLE, VT - (IND)","city":"Morrisville","state":"VT","sales":2190.92,"plan":9367.65,"pctToPlan":23.388149642653175,"gp":952.5966000000001,"gpPct":43.47929636864879,"txns":90,"customers":82},{"store":"39","name":"WINDSOR, VT - (ACE)","city":"Windsor","state":"VT","sales":2164.21,"plan":3645.5,"pctToPlan":59.36661637635441,"gp":828.6927000000001,"gpPct":38.29077122830039,"txns":57,"customers":55},{"store":"104","name":"SOUTHBRIDGE, MA - (ACE)","city":"Southbridge","state":"MA","sales":2149.22,"plan":4944.81,"pctToPlan":43.464157369039455,"gp":930.0149999999999,"gpPct":43.27221038330185,"txns":85,"customers":77},{"store":"225","name":"CAMBRIDGE, NY - ACE","city":"Cambridge","state":"NY","sales":2148.11,"plan":7006.35,"pctToPlan":30.659473192175668,"gp":1081.6735,"gpPct":50.35466060862805,"txns":71,"customers":68},{"store":"44","name":"WALPOLE, NH - ACE","city":"Walpole","state":"NH","sales":2125.9,"plan":4631.59,"pctToPlan":45.90000410226294,"gp":944.1834000000001,"gpPct":44.41334964015241,"txns":55,"customers":51},{"store":"216","name":"ESSEX JUNCTION, VT - ACE","city":"Essex Junction","state":"VT","sales":2104.04,"plan":7351.45,"pctToPlan":28.620748287752757,"gp":868.2621999999999,"gpPct":41.26643029600197,"txns":64,"customers":58},{"store":"159","name":"COTUIT, MA - (ACE)","city":"Marstons Mills","state":"MA","sales":2084.88,"plan":7098.67,"pctToPlan":29.370008748117606,"gp":915.0011000000002,"gpPct":43.88747074172135,"txns":66,"customers":61},{"store":"70","name":"PUTNAM, CT - (ACE)","city":"Putnam","state":"CT","sales":2078.39,"plan":3750.84,"pctToPlan":55.411321197385114,"gp":812.3393999999998,"gpPct":39.08503216431949,"txns":61,"customers":56},{"store":"133","name":"WATERVILLE, ME - ACE","city":"Waterville","state":"ME","sales":2065.37,"plan":5658.06,"pctToPlan":36.50314772201072,"gp":943.1713,"gpPct":45.6659726828607,"txns":68,"customers":64},{"store":"163","name":"WARNER, NH - (IND)","city":"Warner","state":"NH","sales":2047.94,"plan":3924.24,"pctToPlan":52.18692026991214,"gp":889.4285,"gpPct":43.43039835151421,"txns":51,"customers":47},{"store":"229","name":"PLYMOUTH, NH - ACE","city":"Plymouth","state":"NH","sales":2032.62,"plan":6088.46,"pctToPlan":33.38479681233021,"gp":887.9246999999998,"gpPct":43.68375298875342,"txns":73,"customers":65},{"store":"51","name":"WATERBURY, VT - (ACE)","city":"Waterbury","state":"VT","sales":1999.27,"plan":4833.7,"pctToPlan":41.3610691602706,"gp":920.8734999999999,"gpPct":46.060487077783385,"txns":69,"customers":59},{"store":"222","name":"ROYERSFORD, PA - ACE","city":"Royersford","state":"PA","sales":1950.93,"plan":11070.23,"pctToPlan":17.623211080528588,"gp":854.2848000000001,"gpPct":43.788593132506044,"txns":78,"customers":71},{"store":"18","name":"SHELBURNE FALLS, MA - ACE","city":"Shelburne Falls","state":"MA","sales":1945.3,"plan":4121.31,"pctToPlan":47.20101132892211,"gp":728.9854,"gpPct":37.47418907109443,"txns":68,"customers":60},{"store":"106","name":"LINCOLN, ME - (ACE)","city":"Lincoln","state":"ME","sales":1878.19,"plan":5760.49,"pctToPlan":32.604691614775824,"gp":805.5102000000002,"gpPct":42.887577934074834,"txns":72,"customers":67},{"store":"89","name":"WAREHAM, MA - ACE","city":"Wareham","state":"MA","sales":1833.79,"plan":4521.35,"pctToPlan":40.55846152144824,"gp":945.4951,"gpPct":51.55961696813702,"txns":62,"customers":56},{"store":"97","name":"LISBON FALLS, ME - ACE","city":"Lisbon Falls","state":"ME","sales":1821.02,"plan":5547.19,"pctToPlan":32.82779208932811,"gp":747.113,"gpPct":41.02717158515558,"txns":68,"customers":64},{"store":"197","name":"DOYLESTOWN, PA - IND","city":"Doylestown","state":"PA","sales":1786.06,"plan":7280.3,"pctToPlan":24.532780242572418,"gp":867.3997999999999,"gpPct":48.56498661859064,"txns":71,"customers":67},{"store":"232","name":"RICHMOND, RI - ACE","city":"Richmond","state":"RI","sales":1749.76,"plan":3772.75,"pctToPlan":46.378901331919685,"gp":808.9272,"gpPct":46.23075164594002,"txns":63,"customers":57},{"store":"181","name":"PLYMOUTH, MA - (ACE)","city":"Plymouth","state":"MA","sales":1746.01,"plan":3776.17,"pctToPlan":46.23758993901228,"gp":751.9363,"gpPct":43.06597900355668,"txns":53,"customers":50},{"store":"62","name":"HARDWICK, VT - (ACE)","city":"Hardwick","state":"VT","sales":1703.59,"plan":3197.75,"pctToPlan":53.27464623563443,"gp":797.8870999999999,"gpPct":46.83562946483602,"txns":48,"customers":43},{"store":"84","name":"TICONDEROGA, NY- ACE","city":"Ticonderoga","state":"NY","sales":1683.48,"plan":4708.62,"pctToPlan":35.75315060463575,"gp":783.2337,"gpPct":46.52468101789151,"txns":57,"customers":50},{"store":"79","name":"FAIR HAVEN, VT - (IND)","city":"Fair Haven","state":"VT","sales":1665.87,"plan":5563.36,"pctToPlan":29.943595237410488,"gp":717.3396999999999,"gpPct":43.060965141337554,"txns":61,"customers":53},{"store":"140","name":"WEST CARTHAGE, NY - (IND)","city":"Carthage","state":"NY","sales":1665.46,"plan":5310.59,"pctToPlan":31.36111053574085,"gp":802.1553,"gpPct":48.16418887274387,"txns":55,"customers":51},{"store":"173","name":"SHELBURNE, VT - (ACE)","city":"Shelburne","state":"VT","sales":1661.48,"plan":5586.86,"pctToPlan":29.73906630916114,"gp":441.31899999999996,"gpPct":26.56180032260394,"txns":59,"customers":53},{"store":"1","name":"FITCHBURG,  MA - IND","city":"Fitchburg","state":"MA","sales":1587.85,"plan":4684.04,"pctToPlan":33.89915542992801,"gp":749.7489999999999,"gpPct":47.217873224800826,"txns":56,"customers":53},{"store":"191","name":"BRISTOL, NH - ACE","city":"Bristol","state":"NH","sales":1539.53,"plan":6751.71,"pctToPlan":22.80207532610257,"gp":730.8106,"gpPct":47.46972127857204,"txns":60,"customers":54},{"store":"34","name":"STAFFORD SPRINGS, CT - ACE","city":"Stafford Springs","state":"CT","sales":1530.61,"plan":6190.74,"pctToPlan":24.72418483089259,"gp":672.6160999999998,"gpPct":43.94431631833059,"txns":77,"customers":65},{"store":"120","name":"PLATTSBURGH, NY - (IND)","city":"Plattsburgh","state":"NY","sales":1525.64,"plan":3672.95,"pctToPlan":41.5371840074055,"gp":740.2114000000001,"gpPct":48.51809076846439,"txns":57,"customers":53},{"store":"195","name":"ALEXANDRIA, VA - (ACE)","city":"Alexandria","state":"VA","sales":1512.21,"plan":6188.95,"pctToPlan":24.434031620872684,"gp":585.4039,"gpPct":38.71181251281238,"txns":50,"customers":45},{"store":"228","name":"NEW BRITAIN, PA - ACE","city":"NEW BRITAIN","state":"PA","sales":1432.04,"plan":5895.41,"pctToPlan":24.290761796041327,"gp":519.1066999999999,"gpPct":36.24945532247702,"txns":43,"customers":34},{"store":"187","name":"LANCASTER, NH - (IND)","city":"Lancaster","state":"NH","sales":1428.36,"plan":6228.79,"pctToPlan":22.931580611964762,"gp":695.574,"gpPct":48.69738721330757,"txns":46,"customers":43},{"store":"91","name":"MANCHESTER, VT - (ACE)","city":"Manchester Center","state":"VT","sales":1404.75,"plan":5153.67,"pctToPlan":27.25727491282911,"gp":710.5433,"gpPct":50.58147713116213,"txns":54,"customers":49},{"store":"164","name":"BUXTON, ME - IND","city":"Buxton","state":"ME","sales":1398.23,"plan":5227.85,"pctToPlan":26.745794160123186,"gp":628.4255,"gpPct":44.94435822432648,"txns":61,"customers":56},{"store":"199","name":"RICHBORO, PA - IND","city":"Richboro","state":"PA","sales":1393.56,"plan":5618.74,"pctToPlan":24.80200187230589,"gp":591.7444999999999,"gpPct":42.46279313413128,"txns":58,"customers":53},{"store":"155","name":"SANDWICH, MA - (IND)","city":"Sandwich","state":"MA","sales":1379.51,"plan":3774.57,"pctToPlan":36.547474281838724,"gp":649.4511,"gpPct":47.07839015302535,"txns":70,"customers":57},{"store":"80","name":"ALLENSTOWN, NH - ACE","city":"Allenstown","state":"NH","sales":1365.91,"plan":5196.22,"pctToPlan":26.286608342218,"gp":681.3068000000001,"gpPct":49.87933319179155,"txns":46,"customers":43},{"store":"17","name":"TURNERS FALLS, MA - (IND)","city":"Turners Falls","state":"MA","sales":1347.82,"plan":4281.08,"pctToPlan":31.48317714221645,"gp":650.1092,"gpPct":48.234126218634536,"txns":70,"customers":61},{"store":"69","name":"LUNENBURG, MA - (IND)","city":"Lunenburg","state":"MA","sales":1345.04,"plan":1999.75,"pctToPlan":67.26040755094387,"gp":710.2155,"gpPct":52.80255605781241,"txns":39,"customers":36},{"store":"107","name":"NORTH WINDHAM, ME - ACE","city":"Windham","state":"ME","sales":1337.42,"plan":3113.18,"pctToPlan":42.95993164545578,"gp":629.0672000000001,"gpPct":47.03587504299323,"txns":49,"customers":44},{"store":"10","name":"PERU, NY - ACE","city":"Peru","state":"NY","sales":1315.41,"plan":3706.21,"pctToPlan":35.492052528054266,"gp":671.8129000000001,"gpPct":51.0725097118009,"txns":51,"customers":44},{"store":"75","name":"ELIZABETHTOWN, NY - ACE","city":"Elizabethtown","state":"NY","sales":1310.07,"plan":3628.5,"pctToPlan":36.105002066969824,"gp":515.0527999999999,"gpPct":39.31490683703924,"txns":50,"customers":48},{"store":"168","name":"HILLSBORO, NH - (IND)","city":"Hillsboro","state":"NH","sales":1284.12,"plan":4019.38,"pctToPlan":31.948210918101793,"gp":605.0180999999999,"gpPct":47.11538641248481,"txns":54,"customers":48},{"store":"223","name":"DUBLIN, PA - ACE","city":"Dublin","state":"PA","sales":1262.3,"plan":6056.79,"pctToPlan":20.841072581350847,"gp":673.2293999999999,"gpPct":53.33354986928622,"txns":55,"customers":50},{"store":"196","name":"BLUE BELL, PA - ACE","city":"Blue Bell","state":"PA","sales":1252.9,"plan":4450.02,"pctToPlan":28.15492964076566,"gp":586.2827000000001,"gpPct":46.794053795195154,"txns":46,"customers":42},{"store":"55","name":"NEWPORT, NH - ACE","city":"Newport","state":"NH","sales":1243.71,"plan":3709.18,"pctToPlan":33.530591667160934,"gp":389.1731000000001,"gpPct":31.291305851042452,"txns":43,"customers":41},{"store":"76","name":"SWANTON, VT - (IND)","city":"Swanton","state":"VT","sales":1223.18,"plan":2627.86,"pctToPlan":46.546619682935926,"gp":610.7592000000001,"gpPct":49.93207868016155,"txns":39,"customers":36},{"store":"194","name":"MONROE, CT - (ACE)","city":"Monroe","state":"CT","sales":1191.76,"plan":3739.69,"pctToPlan":31.86788209717918,"gp":560.9437,"gpPct":47.06851211653353,"txns":44,"customers":40},{"store":"176","name":"NEWMARKET, NH - (ACE)","city":"Newmarket","state":"NH","sales":1139.77,"plan":5513.16,"pctToPlan":20.67362456377105,"gp":388.8786,"gpPct":34.1190415610167,"txns":51,"customers":46},{"store":"101","name":"WINCHESTER, NH - (ACE)","city":"Winchester","state":"NH","sales":1118.31,"plan":4328.5,"pctToPlan":25.835970890608756,"gp":560.9295,"gpPct":50.15867693215655,"txns":44,"customers":40},{"store":"40","name":"BREWER, ME - (ACE)","city":"Brewer","state":"ME","sales":1007.71,"plan":3804.78,"pctToPlan":26.485368405006334,"gp":336.8258000000001,"gpPct":33.42487421976561,"txns":30,"customers":27},{"store":"177","name":"RICHFIELD SPRINGS, NY - ACE","city":"Richfield Springs","state":"NY","sales":1006.88,"plan":4617.05,"pctToPlan":21.807864328954636,"gp":500.9169,"gpPct":49.74941403146353,"txns":39,"customers":36},{"store":"193","name":"SUDBURY, MA - (IND)","city":"Sudbury","state":"MA","sales":875.61,"plan":3033.42,"pctToPlan":28.865439009434894,"gp":402.6883,"gpPct":45.98945877730954,"txns":41,"customers":33},{"store":"100","name":"MILTON, VT - (IND)","city":"Milton","state":"VT","sales":856.04,"plan":3532.46,"pctToPlan":24.233536968571475,"gp":437.37309999999997,"gpPct":51.09260081304612,"txns":45,"customers":35},{"store":"148","name":"AYER, MA - (IND)","city":"Ayer","state":"MA","sales":825.06,"plan":3454.54,"pctToPlan":23.88335350003184,"gp":409.47779999999995,"gpPct":49.63006326812595,"txns":41,"customers":38},{"store":"103","name":"RUMFORD, ME - (ACE)","city":"Rumford","state":"ME","sales":767.18,"plan":3441.21,"pctToPlan":22.293902435480543,"gp":346.35439999999994,"gpPct":45.146432388748394,"txns":47,"customers":40},{"store":"33","name":"GREAT BARRINGTON, MA - (ACE)","city":"Great Barrington","state":"MA","sales":742.5,"plan":3198.4,"pctToPlan":23.214732366183092,"gp":371.0964,"gpPct":49.979313131313134,"txns":44,"customers":40},{"store":"60","name":"GOUVERNEUR, NY - (IND)","city":"Gouverneur","state":"NY","sales":661.76,"plan":2506.26,"pctToPlan":26.4042836736811,"gp":342.02389999999997,"gpPct":51.68397908607349,"txns":27,"customers":24},{"store":"92","name":"BERLIN, NH - (IND)","city":"Berlin","state":"NH","sales":483.48,"plan":2471.82,"pctToPlan":19.559676675486077,"gp":251.67270000000002,"gpPct":52.05441796971954,"txns":25,"customers":22},{"store":"64","name":"AUGUSTA, ME - (ACE)","city":"Augusta","state":"ME","sales":92.8,"plan":2688.18,"pctToPlan":3.4521497816366464,"gp":50.5631,"gpPct":54.486099137931035,"txns":11,"customers":7}],"topProducts":[{"product":"REGAL,SLCT.EGSHL,PSTL 1G#5491X","productCode":500808,"sales":6574.11},{"product":"MIDWEST NUTS & BOLTS","productCode":25,"sales":6480.42},{"product":"REGAL,SLCT.MATTE,PSTL.1G#5481X","productCode":500816,"sales":2663.64},{"product":"BEN,INT.EGSHL,PASTEL,1G #N6261","productCode":122413,"sales":2493.57},{"product":"SCOTTS  4 STEP 15M","productCode":15000,"sales":2319.92},{"product":"PFQ97HSPVDS GEP WASH/DRY COMBO","productCode":759542,"sales":2249.95},{"product":"ULTRSPC-500,L/S.PSTL.1G #5371","productCode":140840,"sales":1907.64},{"product":"REGAL,SLCT.PEARL,PSTL.1G#5501X","productCode":128578,"sales":1855.75},{"product":"CEILING,WTRBORN,WHT.1G #N50809","productCode":122385,"sales":1507.74},{"product":"REGAL,SLCT.S.GLS,PSTL.1G#5511X","productCode":500800,"sales":1412.81},{"product":"CONCRETE,MIX,80-LB.    #110180","productCode":219022,"sales":1351.36},{"product":"WOODLUXE WB D/S STN SLD B4 GL","productCode":792745,"sales":1349.82},{"product":"PRIMER, B-I-N, 5-GALLON  #0900","productCode":155259,"sales":1259.97},{"product":"POKEMON - PERFECT ORDER BOOST","productCode":963314,"sales":1222.47},{"product":"FRESHSTRT,SUPRIOR,WHT.1G#04600","productCode":500833,"sales":1218.77},{"product":"ULTRSPC-500,FLAT,WHT.5G#T53501","productCode":140828,"sales":1217.94},{"product":"ULTRSPC-500,EGSH.PSTL.5G#5381","productCode":140852,"sales":1169.95},{"product":"WOODRIDGE PRO TRAEGER","productCode":848345,"sales":1149},{"product":"WOODLUXE WB D/S STN SLD B3 GL","productCode":792743,"sales":1124.85},{"product":"BEN,INT.EGSHL,PASTEL,5G #N6261","productCode":122478,"sales":1119.96},{"product":"MOORGARD,LLUST.PASTL,5G#W1031X","productCode":133632,"sales":1109.97},{"product":"CEILING,WTRBORN,PSTL.5G #05081","productCode":122388,"sales":1079.96},{"product":"BR600Z BLOWER, BACKPACK","productCode":410926,"sales":1049.98},{"product":"MOORGARD,LLUST.PASTL,1G#W1031X","productCode":133630,"sales":1039.87},{"product":"2CUFT/50QT MG POTTING MIX","productCode":102836,"sales":1019.5},{"product":"PROPANE, TANK, EX 20LB","productCode":105,"sales":1018.62},{"product":"TRUFUEL 50:1 2CYCLE 110 OZ","productCode":705228,"sales":1014.65},{"product":"FINAL TOUCH FLAT WH 5G","productCode":188346,"sales":991.92},{"product":"SCOTTS 4 STEP 5M","productCode":5000,"sales":959.92},{"product":"PELLET,GREEN SUPREME,BLEND40LB","productCode":129991,"sales":958.8},{"product":"ULTRSPC-500,EGSH.PSTL.1G#5381","productCode":140851,"sales":953.82},{"product":"BROWN SCOTTS MULCH","productCode":133666,"sales":952.19},{"product":"RED SCOTTS MULCH","productCode":108475,"sales":916.42},{"product":"2BRNR BLACKSTONE GRIDDLE","productCode":851139,"sales":899.97},{"product":"BLACK SCOTTS MULCH","productCode":114960,"sales":882.25},{"product":"SAND,TRACTION,TUBE,60-LB.","productCode":308569,"sales":879.12},{"product":"AURA,INT.MATTE,PSTL,1G  #05221","productCode":122338,"sales":863.91},{"product":"PREMIUM TOP SOIL .75CF","productCode":225006,"sales":860.28},{"product":".75CU.FT MG GARDEN SOIL","productCode":937435,"sales":860.01},{"product":"1.5CF MG ORG BED/GARDEN SOIL","productCode":765126,"sales":827},{"product":"WOODLUXE WB D/S STN SLD B1 GL","productCode":792739,"sales":824.89},{"product":"SPIRIT E-210LP BLK","productCode":825446,"sales":798},{"product":"AURA,INT.EGSHL,PSTL,1G  #05241","productCode":122347,"sales":767.92},{"product":"8 CUFT WHEELBARROW,2WHL","productCode":142539,"sales":751.96},{"product":"BR 800 C-E MAGNUM BLOWER","productCode":194535,"sales":749.99},{"product":"FRESHSTRT,SUPRIOR,WHT.5G#04600","productCode":500831,"sales":749.97},{"product":"DETECTOR,SMOKE,CO,PE #SC7010BV","productCode":125580,"sales":749.9},{"product":"REGAL,SLCT.EGSHL,DEEP.1G#5493X","productCode":500804,"sales":739.9},{"product":"1/2X4X8 WATER RESISTANT SHTRCK","productCode":364192,"sales":734.7},{"product":"MDB4949SKW MAYTAG DW","productCode":759494,"sales":732.95},{"product":"REGAL,SLCT.EGSHL,PSTL.5G#5491X","productCode":128733,"sales":729.98},{"product":"REGAL,SLCT.MATTE,PSTL.5G#5481X","productCode":129892,"sales":729.98},{"product":"WOODLUXE WB D/S STN SLD B2 5G","productCode":792742,"sales":719.98},{"product":"SUN/SHADE 12006 25LB","productCode":637557,"sales":719.94},{"product":"MOORGARD,LLUST.DEEP,1G #W1033X","productCode":133636,"sales":719.91},{"product":"COMPOST, BULK","productCode":117575,"sales":715},{"product":"ULTRSPC-500,L/S.PSTL.5G #5371","productCode":140841,"sales":701.97},{"product":"MSA60 C-B W/AK20 AL101","productCode":744199,"sales":699.98},{"product":"FRESHSTRT,FASTDRY,WHT.1G#09400","productCode":110112,"sales":699.9},{"product":"BEN INT LATEX MATTE PASTE GL","productCode":589137,"sales":695.88},{"product":"525PT5S TELESCOPIC P/SOPIC","productCode":251550,"sales":689.99},{"product":"CRYSTALS,SOLAR SALT, 40LB","productCode":604998,"sales":661.6},{"product":"RAPID GRASS, SUNSHADE 16LB","productCode":385678,"sales":659.94},{"product":"REGAL,SLCT.EGSHL,MEDM.1G#5492X","productCode":500806,"sales":659.92},{"product":"LM2135SP 21\" SELECT CUT SP LAW","productCode":736741,"sales":649},{"product":"5/8 X 100' ZERO-G LIGHTWEIGHT","productCode":189542,"sales":629.91},{"product":"3CF NATURAL CEDAR MULCH","productCode":126465,"sales":615.12},{"product":"STEP 1 CRAB & FERT15000","productCode":134239,"sales":599.94},{"product":"PLASTER OF PARIS DRY MIX 25LB","productCode":613921,"sales":593.78},{"product":"REGAL,SLCT.EGSHL,ULTR.1G#5494X","productCode":500802,"sales":591.92},{"product":"REGAL,SLCT.S.GLS,WHT.1G #55101","productCode":129878,"sales":591.92},{"product":"WHEELBARROW 6CF POLY","productCode":342024,"sales":584.91},{"product":"US SCUFF-X INT MAT BASE 1 GAL","productCode":259082,"sales":559.93},{"product":"PROPANE,TANK, 20LB W/OPD VALVE","productCode":161927,"sales":559.92},{"product":"PRIMER-SEALER,B-I-N,GAL.#00901","productCode":265116,"sales":557.94},{"product":"WILD BIRD FOOD 20# ACE","productCode":781035,"sales":554.97},{"product":"SOIL, BLACK EARTH 1CU.FT","productCode":131316,"sales":545.58},{"product":"GRASS SEED, THICK 'R LAWN 40LB","productCode":193502,"sales":540.92},{"product":"KM 131 R LOOP HNDL KOMBISYSTEM","productCode":130744,"sales":539.99},{"product":"FLOOR&PATIO,LTX,DEEP,1G#N1223X","productCode":134313,"sales":539.94},{"product":"BEN,INT.S.GLS,WHITE,1G #N62701","productCode":122422,"sales":530.91},{"product":"GRS SED BLKBTY UTRA 25LB","productCode":688849,"sales":519.96},{"product":"WOODLUXE WB STAIN ST TINT GAL","productCode":792732,"sales":511.92},{"product":"WOODLUXE WB STAIN SS TINT GAL","productCode":792735,"sales":510.93},{"product":"DUMP SKU 901","productCode":901,"sales":510.33},{"product":"PRIMER, COVER-STAIN, OIL, GAL","productCode":286526,"sales":509.98},{"product":"21465 22\" 6.25* B&S 150CC OHV,","productCode":403966,"sales":499},{"product":"SUPER HIDE INT FLAT -WH  5G","productCode":849329,"sales":497.97},{"product":"GRUB CNTRL,GRUBEX 5000 #99605","productCode":168187,"sales":497.84},{"product":"GRASS SEED,  EZ-SEED 20LB","productCode":536135,"sales":489.93},{"product":"COMPOST,LBSTR,QUODDY 1CFT-","productCode":116766,"sales":489.65},{"product":"NEW  PARTS / SUPPLIES","productCode":8039,"sales":484.15},{"product":"AURA,BATH&SPA,MATTE,B1,G#05321","productCode":122482,"sales":479.95},{"product":"AURA,INT.MATTE,PSTL,5G  #05221","productCode":122364,"sales":477.99},{"product":"BEN INT LATEX SATN/ PRL PST GL","productCode":589149,"sales":471.92},{"product":"RAPID GRASS, SUN/SHADE 5.6LB","productCode":385672,"sales":461.89},{"product":"OF POTTING SOIL 1.5CF","productCode":133211,"sales":460.87},{"product":"IMPERVO,ALK,SATN.B1.1G#Z2351B","productCode":116902,"sales":455.96},{"product":"HF POTTING SOIL 2CF-","productCode":135404,"sales":455.88},{"product":"HP COMMAND WB ST - CLEAR GL","productCode":933691,"sales":449.95}],"asOf":"2026-04-21T16:00:15.213000","asOfET":"Apr 21, 2026, 12:00 PM","refreshedAt":"2026-04-21T16:11:50.479Z","storeCount":132,"prediction":{"updatedAt":"2026-04-21T16:11:50.491Z","updatedAtET":"Apr 21, 2026, 12:11 PM","dateET":"2026-04-21","dow":2,"season":"spring","current":{"ts":"2026-04-21T16:11:50.491Z","tsET":"Apr 21, 2026, 12:11 PM","dateET":"2026-04-21","hourET":12,"minuteET":11,"dow":2,"sales":367851.1299999999,"plan":1091990,"pctToPlan":33.6863093984377,"gp":156377.56039999984,"gpPct":42.51109963968302,"txns":10533,"customers":9572,"storeCount":132,"asOf":"2026-04-21T16:00:15.213000","asOfET":"Apr 21, 2026, 12:00 PM"},"prediction":{"available":true,"method":"blended (w=0.53 shape + 0.47 level)","confidence":"medium","projectedEOD":918182.5656899614,"projectedPctToPlan":84.08342253042257,"projectedVariance":-173807.43431003857,"band":{"low":781914.3387519789,"high":1054450.792627944},"pctOfDayElapsed":0.4683333333333333,"level_EOD":1069093.5795561,"shape_EOD":785447.252669039,"blendWeight":0.5320393728427393,"factors":{"plan":1091990,"recencyFactor":0.9393,"dowPlanRatio":1.0423,"holidayKey":null,"holidayMult":1,"weatherKey":"normal","weatherMult":1,"weatherSummary":"concord-nh: 51F Sunny | worcester-ma: 50F Sunny | burlington-vt: 49F Sunny | portland-me: 43F Sunny | albany-ny: 52F Mostly Sunny | scranton-pa: 54F Mostly Sunny"},"shapeDetail":{"basePaceFromCurve":0.4683333333333333,"observedPaceCount":0,"blendedPaceAtNow":0.4683333333333333,"historyDays":0,"avgHistoricalEOD":null},"note":"Plan-anchored forecast. Early in the day we trust plan × factors; later we trust the pace curve.","offlineEstimate":{"estimatedCurrent":19853.118333333332,"estimatedEOD":42391,"paceUsed":0.4683333333333333,"perStore":[{"storeCd":"233","name":"ITHACA, NY - DOWNTOWN","dowEOD":28783,"estimatedCurrent":13480.038333333334,"estimatedEOD":28783,"stdev":0.4847},{"storeCd":"234","name":"ITHACA, NY - TRIPHAMMER","dowEOD":13608,"estimatedCurrent":6373.08,"estimatedEOD":13608,"stdev":0.1026}],"source":"RPT_SCORECARD_BY_DAY, 12 weeks (Jan 25 - Apr 17 2026) with 2x weight on last 28 days"},"combinedProjectedEOD":960573.5656899614,"combinedCurrentSales":387704.24833333323,"footnote":"Company total excludes 2 stores not on live feed (233, 234). Estimated contribution: $19,853 so far, +$42,391 to EOD."},"offlineStoresVersion":2,"baselineVersion":8,"weatherRaw":{"mult":1,"key":"normal","season":"spring","summary":"concord-nh: 51F Sunny | worcester-ma: 50F Sunny | burlington-vt: 49F Sunny | portland-me: 43F Sunny | albany-ny: 52F Mostly Sunny | scranton-pa: 54F Mostly Sunny","tagWeights":{"normal":1},"forecasts":[{"station":"concord-nh","weight":0.144,"temp":51,"unit":"F","short":"Sunny","detailed":"Sunny, with a high near 51. West wind 0 to 5 mph."},{"station":"worcester-ma","weight":0.272,"temp":50,"unit":"F","short":"Sunny","detailed":"Sunny, with a high near 50. West wind 2 to 6 mph."},{"station":"burlington-vt","weight":0.224,"temp":49,"unit":"F","short":"Sunny","detailed":"Sunny, with a high near 49. South wind 1 to 8 mph."},{"station":"portland-me","weight":0.152,"temp":43,"unit":"F","short":"Sunny","detailed":"Sunny, with a high near 43. East wind 0 to 15 mph, with gusts as high as 25 mph."},{"station":"albany-ny","weight":0.12,"temp":52,"unit":"F","short":"Mostly Sunny","detailed":"Mostly sunny, with a high near 52. South wind 1 to 7 mph."},{"station":"scranton-pa","weight":0.088,"temp":54,"unit":"F","short":"Mostly Sunny","detailed":"Mostly sunny, with a high near 54. Southwest wind 1 to 8 mph."}]}},"snapshotAt":"2026-04-21T16:11:52.352Z"}