{"status":"ok","cached":false,"companyTotal":{"sales":747674.1299999999,"plan":997060.8500000003,"gp":312435.4750999998,"gpPct":41.78765354633841,"txns":20575,"customers":19033,"storeCount":134,"pctToPlan":74.98781343184818},"topStores":[{"store":"210","name":"QUINCY, MA - ACE","city":"Quincy","state":"MA","sales":30123.7,"plan":20475.25,"pctToPlan":147.12250155675756,"gp":10554.616300000002,"gpPct":35.03758270066427,"txns":325,"customers":296},{"store":"209","name":"MOUNT JOY, PA - ACE","city":"Mount Joy","state":"PA","sales":24317.63,"plan":31036.62,"pctToPlan":78.35141197720628,"gp":8994.240800000001,"gpPct":36.986502385306466,"txns":546,"customers":518},{"store":"192","name":"BEVERLY, MA - ACE","city":"Beverly","state":"MA","sales":22243.25,"plan":23620.4,"pctToPlan":94.1696584308479,"gp":8268.1412,"gpPct":37.17146190417318,"txns":413,"customers":390},{"store":"153","name":"KINGSTON, MA - ACE","city":"Kingston","state":"MA","sales":14666.23,"plan":14233.21,"pctToPlan":103.04232144400314,"gp":5579.494499999999,"gpPct":38.0431406025952,"txns":247,"customers":234},{"store":"178","name":"DOVER, NH - IND","city":"Dover","state":"NH","sales":13898.32,"plan":5585.87,"pctToPlan":248.81209193912497,"gp":6866.191,"gpPct":49.40302856748154,"txns":138,"customers":125},{"store":"208","name":"BURTONSVILLE, MD - ACE","city":"Burtonsville","state":"MD","sales":13765.95,"plan":20540.29,"pctToPlan":67.01925824805784,"gp":5001.006000000001,"gpPct":36.32881130615759,"txns":228,"customers":215},{"store":"217","name":"NORTH SPRINGFIELD, VT - ACE","city":"North Springfield","state":"VT","sales":13696.14,"plan":20105.46,"pctToPlan":68.12149535499313,"gp":5441.6266,"gpPct":39.731096498721534,"txns":276,"customers":248},{"store":"172","name":"FALMOUTH, MA - (IND)","city":"Teaticket","state":"MA","sales":12329.79,"plan":16449.18,"pctToPlan":74.95686715082455,"gp":4601.871800000001,"gpPct":37.323196907652125,"txns":292,"customers":275},{"store":"171","name":"BELFAST, ME - ACE","city":"Belfast","state":"ME","sales":12267.05,"plan":14207.66,"pctToPlan":86.34110050493888,"gp":4900.840499999999,"gpPct":39.95125559934947,"txns":235,"customers":194},{"store":"6","name":"MOULTONBORO, NH - (IND)","city":"Moultonboro","state":"NH","sales":12136.73,"plan":10017.82,"pctToPlan":121.15140819060434,"gp":4670.9495,"gpPct":38.4860625555648,"txns":199,"customers":189},{"store":"236","name":"DOVER, PA - ACE","city":"Dover","state":"PA","sales":11989.24,"plan":13977.43,"pctToPlan":85.77571127167154,"gp":5041.1493,"gpPct":42.04727989430523,"txns":376,"customers":355},{"store":"202","name":"EASTCHESTER, NY - (ACE)","city":"Eastchester","state":"NY","sales":10071.86,"plan":14883.67,"pctToPlan":67.67054093513227,"gp":4730.4008,"gpPct":46.96650668297613,"txns":328,"customers":315},{"store":"182","name":"COHASSET, MA - (IND)","city":"Cohasset","state":"MA","sales":9522.41,"plan":11544.98,"pctToPlan":82.48095709130722,"gp":3768.3041999999996,"gpPct":39.57300935372452,"txns":207,"customers":192},{"store":"167","name":"ALTON, NH - ACE","city":"Alton","state":"NH","sales":9326.27,"plan":7211.85,"pctToPlan":129.31869076589223,"gp":3783.5194,"gpPct":40.56840944986581,"txns":170,"customers":156},{"store":"83","name":"VERGENNES, VT - ACE","city":"Vergennes","state":"VT","sales":9217.97,"plan":10099.99,"pctToPlan":91.2671200664555,"gp":4060.9978999999994,"gpPct":44.055230164559006,"txns":216,"customers":204},{"store":"230","name":"WOODBURY,  CT - ACE","city":"Woodbury","state":"CT","sales":8922.02,"plan":10656.58,"pctToPlan":83.72310816415774,"gp":3650.8883000000005,"gpPct":40.91997440041605,"txns":248,"customers":223},{"store":"231","name":"WATERTOWN, CT - ACE","city":"Watertown","state":"CT","sales":8801.44,"plan":9242.49,"pctToPlan":95.22801755803903,"gp":3326.757600000001,"gpPct":37.79787852896799,"txns":223,"customers":217},{"store":"190","name":"IPSWICH, MA - ACE","city":"Ipswich","state":"MA","sales":8619.97,"plan":11117.34,"pctToPlan":77.5362631708664,"gp":3637.3031999999994,"gpPct":42.19623966208699,"txns":210,"customers":196},{"store":"213","name":"BRATTLEBORO, VT - ACE","city":"Brattleboro","state":"VT","sales":8513.42,"plan":10144.5,"pctToPlan":83.9215338360688,"gp":3416.6155,"gpPct":40.1321149432308,"txns":211,"customers":199},{"store":"195","name":"ALEXANDRIA, VA - (ACE)","city":"Alexandria","state":"VA","sales":8376.29,"plan":8355.45,"pctToPlan":100.24941804450987,"gp":3109.048600000001,"gpPct":37.11725119354751,"txns":144,"customers":137}],"topProducts":[{"product":"ULTRSPC-EXT,SATN.MEDM.5G#W4482","sales":11199.65},{"product":"REGAL,SLCT.EGSHL,PSTL 1G#5491X","sales":9475.72},{"product":"MIDWEST NUTS & BOLTS","sales":9298.65},{"product":"SCOTTS  4 STEP 15M","sales":6379.78},{"product":"2CUFT/50QT MG POTTING MIX","sales":5338.25},{"product":"WALLPAPER PRIMER 5GAL","sales":5039.76},{"product":"BEN INT LATEX SATN/ PRL PS 5G","sales":4929.83},{"product":"BLACK SCOTTS MULCH","sales":3144.81},{"product":"SCOTTS 4 STEP 5M","sales":3119.74},{"product":"GREEN-UP CRABGRASS PREVENT 15M","sales":3074.59},{"product":"BROWN SCOTTS MULCH","sales":3039.15},{"product":"STEP 1 CRAB & FERT15000","sales":2999.7},{"product":"SPIRIT E-325LP BLK","sales":2994},{"product":"REGAL,SLCT.MATTE,PSTL.1G#5481X","sales":2889.61},{"product":".75CU.FT MG GARDEN SOIL","sales":2656.74},{"product":"BEN,INT.EGSHL,PASTEL,1G #N6261","sales":2599.55},{"product":"GRS SED BLKBTY UTRA 25LB","sales":2469.81},{"product":"FRTLZR,ORGAN PROGRO 5-3-4 50LB","sales":2399.5},{"product":"5/4X6X16TREX ENHNC TOAST SAND","sales":2243.52},{"product":"BEN INT LATEX MATTE PASTEL 5G","sales":2239.92}],"asOf":"2026-04-15T18:45:12.987000","asOfET":"Apr 15, 2026, 2:45 PM","refreshedAt":"2026-04-15T19:05:52.814Z","storeCount":134,"prediction":{"updatedAt":"2026-04-15T19:05:52.823Z","updatedAtET":"Apr 15, 2026, 3:05 PM","dateET":"2026-04-15","dow":3,"current":{"ts":"2026-04-15T19:05:52.823Z","tsET":"Apr 15, 2026, 3:05 PM","dateET":"2026-04-15","hourET":15,"minuteET":5,"dow":3,"sales":747674.1299999999,"plan":997060.8500000003,"pctToPlan":74.98781343184818,"gp":312435.4750999998,"gpPct":41.78765354633841,"txns":20575,"customers":19033,"storeCount":134,"asOf":"2026-04-15T18:45:12.987000","asOfET":"Apr 15, 2026, 2:45 PM"},"prediction":{"available":true,"method":"cold-start linear (business hours)","confidence":"very low","historyDays":0,"assumedBusinessHours":"7 AM – 8 PM ET","pctOfDayElapsed":0.6217948717948718,"projectedEOD":1202444.9925773195,"projectedPctToPlan":120.59895768420945,"projectedVariance":205384.14257731917,"note":"Sales assumed to accumulate evenly across business hours. This is a naive starting point — every new run, once any history exists, it will be replaced by a pace-curve projection."}},"snapshotAt":"2026-04-15T19:05:54.407Z"}