{"status":"ok","cached":false,"companyTotal":{"sales":452848.63999999984,"plan":1073381.2100000002,"gp":190478.56849999976,"gpPct":42.06230331176435,"txns":12518,"customers":11496,"storeCount":133,"pctToPlan":42.188985216165634},"topStores":[{"store":"198","name":"LYNDONVILLE, VT - ACE","city":"Lyndonville","state":"VT","sales":12126.94,"plan":12904.63,"pctToPlan":93.97355832751502,"gp":3962.4743000000008,"gpPct":32.674972416784456,"txns":146,"customers":136},{"store":"209","name":"MOUNT JOY, PA - ACE","city":"Mount Joy","state":"PA","sales":12042.87,"plan":33201.54,"pctToPlan":36.272022321856156,"gp":4875.1724,"gpPct":40.48181538121727,"txns":314,"customers":302},{"store":"210","name":"QUINCY, MA - ACE","city":"Quincy","state":"MA","sales":10615.93,"plan":19276.5,"pctToPlan":55.07187508105724,"gp":3842.0755,"gpPct":36.19160544577818,"txns":163,"customers":156},{"store":"192","name":"BEVERLY, MA - ACE","city":"Beverly","state":"MA","sales":9105.26,"plan":28185.55,"pctToPlan":32.30470932800673,"gp":4247.5960000000005,"gpPct":46.649914445057036,"txns":243,"customers":227},{"store":"172","name":"FALMOUTH, MA - (IND)","city":"Teaticket","state":"MA","sales":8947.81,"plan":17998.41,"pctToPlan":49.71444699837374,"gp":3229.4856999999993,"gpPct":36.0924706715945,"txns":171,"customers":157},{"store":"6","name":"MOULTONBORO, NH - (IND)","city":"Moultonboro","state":"NH","sales":8485.51,"plan":11947.47,"pctToPlan":71.02348865492026,"gp":3369.0116,"gpPct":39.703112718033445,"txns":158,"customers":149},{"store":"153","name":"KINGSTON, MA - ACE","city":"Kingston","state":"MA","sales":6987.32,"plan":14095.67,"pctToPlan":49.57068376316982,"gp":1856.4052000000001,"gpPct":26.568200683523873,"txns":112,"customers":101},{"store":"83","name":"VERGENNES, VT - ACE","city":"Vergennes","state":"VT","sales":6947.9,"plan":11991.49,"pctToPlan":57.94025596485507,"gp":2965.4738999999995,"gpPct":42.68158580290447,"txns":152,"customers":146},{"store":"63","name":"MIDDLEBURY, VT - ACE","city":"Middlebury","state":"VT","sales":6608.51,"plan":10592.78,"pctToPlan":62.38692769981063,"gp":2778.4910000000004,"gpPct":42.04413702937577,"txns":143,"customers":128},{"store":"182","name":"COHASSET, MA - (IND)","city":"Cohasset","state":"MA","sales":6472.23,"plan":11354.94,"pctToPlan":56.99924438174045,"gp":2409.9542999999994,"gpPct":37.23530066144126,"txns":149,"customers":135},{"store":"190","name":"IPSWICH, MA - ACE","city":"Ipswich","state":"MA","sales":5965.13,"plan":8945.14,"pctToPlan":66.68570866414612,"gp":2438.8064,"gpPct":40.88437972014021,"txns":144,"customers":131},{"store":"217","name":"NORTH SPRINGFIELD, VT - ACE","city":"North Springfield","state":"VT","sales":5905.83,"plan":20038.09,"pctToPlan":29.473018636007726,"gp":2605.5394,"gpPct":44.11809009063925,"txns":166,"customers":151},{"store":"202","name":"EASTCHESTER, NY - (ACE)","city":"Eastchester","state":"NY","sales":5751.93,"plan":15915.7,"pctToPlan":36.139974993245666,"gp":2661.9129000000003,"gpPct":46.278603877307276,"txns":159,"customers":152},{"store":"236","name":"DOVER, PA - ACE","city":"Dover","state":"PA","sales":5685.6,"plan":16268.01,"pctToPlan":34.94957281191738,"gp":2396.8494000000005,"gpPct":42.15649008020262,"txns":197,"customers":181},{"store":"171","name":"BELFAST, ME - ACE","city":"Belfast","state":"ME","sales":5675.16,"plan":15833.38,"pctToPlan":35.843010146917464,"gp":2436.8599,"gpPct":42.939051938623756,"txns":116,"customers":104},{"store":"136","name":"LAKE PLACID, NY - ACE","city":"Lake Placid","state":"NY","sales":5557.21,"plan":9175.01,"pctToPlan":60.56898030628849,"gp":2383.4452,"gpPct":42.889241183975415,"txns":112,"customers":105},{"store":"49","name":"BARRE, VT - IND","city":"Barre","state":"VT","sales":5411.37,"plan":12312.53,"pctToPlan":43.950106111416574,"gp":2334.7772,"gpPct":43.14576900119563,"txns":136,"customers":126},{"store":"208","name":"BURTONSVILLE, MD - ACE","city":"Burtonsville","state":"MD","sales":5244.84,"plan":22935.37,"pctToPlan":22.867911003833818,"gp":2262.0268,"gpPct":43.128614028263975,"txns":119,"customers":108},{"store":"4","name":"GARDNER, MA - ACE","city":"Gardner","state":"MA","sales":5037.23,"plan":8905.49,"pctToPlan":56.56319865610988,"gp":2069.3099999999995,"gpPct":41.08031596730742,"txns":129,"customers":121},{"store":"220","name":"PENNSBURG, PA - ACE","city":"Pennsburg","state":"PA","sales":5014.32,"plan":12220.98,"pctToPlan":41.030424728622414,"gp":2169.2481999999995,"gpPct":43.26106431181096,"txns":137,"customers":127},{"store":"167","name":"ALTON, NH - ACE","city":"Alton","state":"NH","sales":4981.17,"plan":8773.44,"pctToPlan":56.775563518984576,"gp":2077.25,"gpPct":41.702049919998714,"txns":106,"customers":99},{"store":"45","name":"MONTPELIER, VT - ACE","city":"Montpelier","state":"VT","sales":4670.56,"plan":8314.34,"pctToPlan":56.17475349817303,"gp":1837.9679000000006,"gpPct":39.35219545407832,"txns":153,"customers":135},{"store":"237","name":"CUMBERLAND, RI - ACE","city":"Cumberland","state":"RI","sales":4543.16,"plan":9685.73,"pctToPlan":46.90570561021214,"gp":2179.9266,"gpPct":47.982606819922694,"txns":129,"customers":122},{"store":"16","name":"NORWAY, ME - ACE","city":"Norway","state":"ME","sales":4471.94,"plan":7323.17,"pctToPlan":61.06563141371837,"gp":2264.6296999999995,"gpPct":50.64087845543545,"txns":103,"customers":97},{"store":"10","name":"PERU, NY - ACE","city":"Peru","state":"NY","sales":4451.02,"plan":3522.81,"pctToPlan":126.34856833039537,"gp":1441.4502000000002,"gpPct":32.38471631221608,"txns":71,"customers":69},{"store":"113","name":"TUPPER LAKE, NY - ACE","city":"Tupper Lake","state":"NY","sales":4444.39,"plan":8926.51,"pctToPlan":49.78866320656113,"gp":2000.7979000000005,"gpPct":45.01850422667679,"txns":122,"customers":113},{"store":"135","name":"NAPLES, ME - ACE","city":"Naples","state":"ME","sales":4391.74,"plan":8462.02,"pctToPlan":51.89942826890033,"gp":1959.9733999999999,"gpPct":44.628630110161346,"txns":119,"customers":102},{"store":"211","name":"HANOVER, MA - ACE","city":"Hanover","state":"MA","sales":4338.81,"plan":10157.32,"pctToPlan":42.71609046480765,"gp":1632.0679000000005,"gpPct":37.61556509734237,"txns":100,"customers":95},{"store":"224","name":"VILLAS, NJ - ACE","city":"Villas","state":"NJ","sales":4315.98,"plan":10378.68,"pctToPlan":41.58505705927921,"gp":1670.6174999999994,"gpPct":38.70772107377697,"txns":147,"customers":127},{"store":"215","name":"COLCHESTER, VT - ACE","city":"Colchester","state":"VT","sales":4250.5,"plan":9373.08,"pctToPlan":45.347953927631046,"gp":2011.3809,"gpPct":47.32104223032585,"txns":140,"customers":125},{"store":"175","name":"LEE, NH - ACE","city":"Lee","state":"NH","sales":4193.73,"plan":11115.31,"pctToPlan":37.729312092960065,"gp":1775.1311999999994,"gpPct":42.32821855484257,"txns":110,"customers":99},{"store":"7","name":"TEWKSBURY, MA - (IND)","city":"Tewksbury","state":"MA","sales":4139.29,"plan":7075.96,"pctToPlan":58.49792819631541,"gp":1672.9341,"gpPct":40.41596747268251,"txns":87,"customers":78},{"store":"219","name":"WOODSTOCK, VT - ACE","city":"Woodstock","state":"VT","sales":4131.75,"plan":8471.14,"pctToPlan":48.774427054682135,"gp":1929.9106000000002,"gpPct":46.70927815090458,"txns":112,"customers":103},{"store":"230","name":"WOODBURY,  CT - ACE","city":"Woodbury","state":"CT","sales":4058.53,"plan":9585.37,"pctToPlan":42.340879903436175,"gp":1593.4150000000004,"gpPct":39.26089002668455,"txns":100,"customers":87},{"store":"227","name":"RUTLAND, VT - ACE","city":"Rutland","state":"VT","sales":4052.23,"plan":10814.39,"pctToPlan":37.47072188075333,"gp":1881.7409000000002,"gpPct":46.437169163645706,"txns":117,"customers":113},{"store":"57","name":"MORRISVILLE, VT - (IND)","city":"Morrisville","state":"VT","sales":4029.48,"plan":8288.14,"pctToPlan":48.61742200300671,"gp":1847.9766,"gpPct":45.86141636141636,"txns":107,"customers":99},{"store":"218","name":"SOUTH BURLINGTON, VT - ACE","city":"South Burlington","state":"VT","sales":3983.51,"plan":9616.65,"pctToPlan":41.423052726261226,"gp":1379.2701000000002,"gpPct":34.624491968138656,"txns":144,"customers":138},{"store":"94","name":"WILLIAMSTOWN, MA - ACE","city":"Williamstown","state":"MA","sales":3946.79,"plan":6443.5,"pctToPlan":61.25226972918445,"gp":1583.7547,"gpPct":40.12766577395808,"txns":95,"customers":84},{"store":"173","name":"SHELBURNE, VT - (ACE)","city":"Shelburne","state":"VT","sales":3945.66,"plan":6280.7,"pctToPlan":62.82197844189342,"gp":1783.9397999999997,"gpPct":45.21270966074116,"txns":79,"customers":72},{"store":"74","name":"EASTHAMPTON, MA - ACE","city":"Easthampton","state":"MA","sales":3897.39,"plan":7642.47,"pctToPlan":50.99647103619641,"gp":1994.4088,"gpPct":51.172933681258485,"txns":128,"customers":121},{"store":"207","name":"FARMINGDALE, ME - ACE","city":"Farmingdale","state":"ME","sales":3818.29,"plan":8677.36,"pctToPlan":44.002899499386906,"gp":1620.5769999999998,"gpPct":42.44248079637743,"txns":89,"customers":82},{"store":"221","name":"PHOENIXVILLE, PA - ACE","city":"Phoenixville","state":"PA","sales":3787.32,"plan":11339.11,"pctToPlan":33.400504977903914,"gp":1651.4069,"gpPct":43.603574559318986,"txns":118,"customers":111},{"store":"118","name":"GREENFIELD, MA - (IND)","city":"Greenfield","state":"MA","sales":3768.75,"plan":6051.25,"pctToPlan":62.280520553604624,"gp":1603.3058999999998,"gpPct":42.54211343283581,"txns":101,"customers":88},{"store":"90","name":"WELLS, ME - (ACE)","city":"Wells","state":"ME","sales":3761.9,"plan":9230.49,"pctToPlan":40.75514950993934,"gp":1588.8043000000002,"gpPct":42.2340918153061,"txns":128,"customers":120},{"store":"3","name":"MEREDITH, NH - (IND)","city":"Meredith","state":"NH","sales":3739.61,"plan":7834.35,"pctToPlan":47.73350692782426,"gp":1581.5946,"gpPct":42.2930359048136,"txns":89,"customers":77},{"store":"231","name":"WATERTOWN, CT - ACE","city":"Watertown","state":"CT","sales":3739.05,"plan":8501.38,"pctToPlan":43.98168297382308,"gp":1564.2152,"gpPct":41.83456225511828,"txns":108,"customers":105},{"store":"32","name":"FRANKLIN, MA - ACE","city":"Franklin","state":"MA","sales":3700.65,"plan":9436.57,"pctToPlan":39.21604989948679,"gp":1323.7215,"gpPct":35.76997284260873,"txns":94,"customers":88},{"store":"183","name":"HINESBURG, VT - ACE","city":"Hinesburg","state":"VT","sales":3686.24,"plan":6723.65,"pctToPlan":54.82498345392756,"gp":1445.5292999999997,"gpPct":39.2141938669213,"txns":104,"customers":96},{"store":"212","name":"BRUNSWICK, MD - ACE","city":"Brunswick","state":"MD","sales":3646.18,"plan":9328.56,"pctToPlan":39.086204087233185,"gp":1801.0176,"gpPct":49.39464316078745,"txns":103,"customers":99},{"store":"42","name":"LUDLOW, VT - ACE","city":"Ludlow","state":"VT","sales":3639.89,"plan":6079.63,"pctToPlan":59.87025526224458,"gp":1279.0634,"gpPct":35.14016632370758,"txns":90,"customers":79},{"store":"132","name":"EASTON, NY - ACE","city":"Greenwich","state":"NY","sales":3633.8,"plan":8735.52,"pctToPlan":41.597981574079164,"gp":1624.9427000000003,"gpPct":44.717450052286864,"txns":106,"customers":91},{"store":"156","name":"SO. SANDWICH, MA - (IND)","city":"Sandwich","state":"MA","sales":3631.88,"plan":8988.63,"pctToPlan":40.40526754355225,"gp":1476.2773000000002,"gpPct":40.64774441886847,"txns":97,"customers":89},{"store":"201","name":"SOUTH ROYALTON, VT - ACE","city":"South Royalton","state":"VT","sales":3614.91,"plan":7933.61,"pctToPlan":45.564503422779794,"gp":1719.5475999999999,"gpPct":47.5681994849111,"txns":87,"customers":80},{"store":"222","name":"ROYERSFORD, PA - ACE","city":"Royersford","state":"PA","sales":3612.82,"plan":10911.21,"pctToPlan":33.1110848384368,"gp":1400.8400000000001,"gpPct":38.7741431900842,"txns":105,"customers":96},{"store":"65","name":"LITTLETON, MA - (IND)","city":"Littleton","state":"MA","sales":3604.31,"plan":8670.27,"pctToPlan":41.57090840308318,"gp":1509.3844,"gpPct":41.87720812027822,"txns":96,"customers":88},{"store":"214","name":"BURLINGTON, VT - ACE","city":"Burlington","state":"VT","sales":3599.64,"plan":6456.21,"pctToPlan":55.75469199421952,"gp":1604.1552,"gpPct":44.564323098976566,"txns":103,"customers":99},{"store":"206","name":"WINSLOW, ME - ACE","city":"Winslow","state":"ME","sales":3588.29,"plan":10054.66,"pctToPlan":35.687830319473754,"gp":1549.7928,"gpPct":43.19028841035702,"txns":115,"customers":109},{"store":"205","name":"SKOWHEGAN, ME - ACE","city":"Skowhegan","state":"ME","sales":3521.37,"plan":8038.17,"pctToPlan":43.80810557626923,"gp":1568.58,"gpPct":44.54459485938712,"txns":74,"customers":70},{"store":"203","name":"BRISTOL, VT - (ACE)","city":"Bristol","state":"VT","sales":3505.67,"plan":8628.74,"pctToPlan":40.62783210526682,"gp":1694.8016,"gpPct":48.344584630042185,"txns":109,"customers":100},{"store":"8","name":"CLINTON, MA - ACE","city":"Clinton","state":"MA","sales":3409.12,"plan":5937.82,"pctToPlan":57.41366360044595,"gp":1539.2111,"gpPct":45.1498069883137,"txns":103,"customers":89},{"store":"213","name":"BRATTLEBORO, VT - ACE","city":"Brattleboro","state":"VT","sales":3400.95,"plan":10529.75,"pctToPlan":32.29848761841449,"gp":1745.7858999999999,"gpPct":51.33230126876314,"txns":112,"customers":106},{"store":"133","name":"WATERVILLE, ME - ACE","city":"Waterville","state":"ME","sales":3395.1,"plan":5436.85,"pctToPlan":62.44608550907235,"gp":1461.9563999999998,"gpPct":43.060775823981615,"txns":83,"customers":79},{"store":"187","name":"LANCASTER, NH - (IND)","city":"Lancaster","state":"NH","sales":3306.11,"plan":7170.2,"pctToPlan":46.1090346154919,"gp":1125.8380000000002,"gpPct":34.053252916569626,"txns":81,"customers":73},{"store":"37","name":"WEBSTER, MA - (ACE)","city":"Webster","state":"MA","sales":3302.61,"plan":6869.57,"pctToPlan":48.075934883842805,"gp":1560.6433000000002,"gpPct":47.25484692409943,"txns":94,"customers":88},{"store":"144","name":"HAVERHILL, MA - ACE","city":"Haverhill","state":"MA","sales":3249.57,"plan":7291.45,"pctToPlan":44.566855700855115,"gp":910.6764000000003,"gpPct":28.02452016728368,"txns":87,"customers":82},{"store":"124","name":"NEWPORT, ME - ACE","city":"Newport","state":"ME","sales":3249.19,"plan":6890.96,"pctToPlan":47.15148542438209,"gp":1428.0343,"gpPct":43.95047073270569,"txns":86,"customers":79},{"store":"25","name":"SAINT JOHNSBURY, VT - ACE","city":"Saint Johnsbury","state":"VT","sales":3191.22,"plan":9480.13,"pctToPlan":33.66219661544726,"gp":1466.0656,"gpPct":45.94059951993282,"txns":104,"customers":91},{"store":"188","name":"STOW, MA - IND","city":"Stow","state":"MA","sales":3132.12,"plan":6888.06,"pctToPlan":45.47172934033675,"gp":1332.4089999999999,"gpPct":42.54016448922774,"txns":86,"customers":79},{"store":"178","name":"DOVER, NH - IND","city":"Dover","state":"NH","sales":3105.88,"plan":5833.42,"pctToPlan":53.242866105989286,"gp":1308.365,"gpPct":42.125420170772855,"txns":77,"customers":70},{"store":"158","name":"POCASSET, MA - ACE","city":"Pocasset","state":"MA","sales":3075.35,"plan":7253.72,"pctToPlan":42.39686671114959,"gp":1403.1788,"gpPct":45.62663761848245,"txns":80,"customers":72},{"store":"189","name":"OSSIPEE, NH - (ACE)","city":"Center Ossipee","state":"NH","sales":3065.9,"plan":6486.3,"pctToPlan":47.26731726870481,"gp":1427.2145,"gpPct":46.55124107113735,"txns":80,"customers":75},{"store":"191","name":"BRISTOL, NH - ACE","city":"Bristol","state":"NH","sales":3048.82,"plan":5423.11,"pctToPlan":56.21903299029525,"gp":1314.9619000000002,"gpPct":43.130191352720075,"txns":90,"customers":83},{"store":"226","name":"COBLESKILL, NY - ACE","city":"Cobleskill","state":"NY","sales":3015.29,"plan":7428.16,"pctToPlan":40.59269051824409,"gp":749.4162000000001,"gpPct":24.85386811882108,"txns":91,"customers":84},{"store":"159","name":"COTUIT, MA - (ACE)","city":"Marstons Mills","state":"MA","sales":2986.79,"plan":6595.51,"pctToPlan":45.285201599269804,"gp":1107.1082,"gpPct":37.06682424944505,"txns":90,"customers":76},{"store":"216","name":"ESSEX JUNCTION, VT - ACE","city":"Essex Junction","state":"VT","sales":2919.08,"plan":7601.58,"pctToPlan":38.40096401011369,"gp":1426.4986999999999,"gpPct":48.86809200158954,"txns":106,"customers":99},{"store":"18","name":"SHELBURNE FALLS, MA - ACE","city":"Shelburne Falls","state":"MA","sales":2910.48,"plan":4287.75,"pctToPlan":67.87895749518978,"gp":1143.2592,"gpPct":39.280778428300486,"txns":74,"customers":66},{"store":"225","name":"CAMBRIDGE, NY - ACE","city":"Cambridge","state":"NY","sales":2910.3,"plan":5236.86,"pctToPlan":55.5733779402161,"gp":1224.9131000000002,"gpPct":42.088894615675365,"txns":93,"customers":87},{"store":"34","name":"STAFFORD SPRINGS, CT - ACE","city":"Stafford Springs","state":"CT","sales":2897.72,"plan":5815.81,"pctToPlan":49.82487392125945,"gp":1407.2185999999997,"gpPct":48.56295984429136,"txns":82,"customers":78},{"store":"152","name":"CARVER, MA - ACE","city":"Carver","state":"MA","sales":2760.08,"plan":4960.03,"pctToPlan":55.6464376223531,"gp":1249.1337999999998,"gpPct":45.257159212776436,"txns":87,"customers":84},{"store":"51","name":"WATERBURY, VT - (ACE)","city":"Waterbury","state":"VT","sales":2720.25,"plan":4018.76,"pctToPlan":67.68878957688442,"gp":1319.9301,"gpPct":48.52238213399504,"txns":69,"customers":65},{"store":"22","name":"LINCOLN, NH - ACE","city":"Lincoln","state":"NH","sales":2706.28,"plan":5466.72,"pctToPlan":49.50463897913191,"gp":1159.4104000000002,"gpPct":42.84147981731381,"txns":78,"customers":70},{"store":"200","name":"NEW HOPE, PA - ACE","city":"New Hope","state":"PA","sales":2560.87,"plan":5943.5,"pctToPlan":43.08690165727265,"gp":1214.7819,"gpPct":47.436297039677925,"txns":102,"customers":96},{"store":"204","name":"MADISON, ME - ACE","city":"Madison","state":"ME","sales":2557.11,"plan":6468.58,"pctToPlan":39.53124178722378,"gp":931.9557000000002,"gpPct":36.445663268298986,"txns":90,"customers":86},{"store":"229","name":"PLYMOUTH, NH - ACE","city":"Plymouth","state":"NH","sales":2499.31,"plan":4890.37,"pctToPlan":51.10676697264215,"gp":1082.9466,"gpPct":43.3298230311566,"txns":87,"customers":78},{"store":"164","name":"BUXTON, ME - IND","city":"Buxton","state":"ME","sales":2443.8,"plan":5146.22,"pctToPlan":47.487281927317525,"gp":1285.5621,"gpPct":52.605045421065554,"txns":81,"customers":75},{"store":"197","name":"DOYLESTOWN, PA - IND","city":"Doylestown","state":"PA","sales":2415.28,"plan":6424.25,"pctToPlan":37.59629528738764,"gp":1119.3751000000002,"gpPct":46.34556241926403,"txns":91,"customers":83},{"store":"232","name":"RICHMOND, RI - ACE","city":"Richmond","state":"RI","sales":2400.73,"plan":3960.01,"pctToPlan":60.62434185772258,"gp":930.4612999999999,"gpPct":38.75743211439853,"txns":86,"customers":82},{"store":"104","name":"SOUTHBRIDGE, MA - (ACE)","city":"Southbridge","state":"MA","sales":2381.14,"plan":4597.38,"pctToPlan":51.793412769881975,"gp":708.5520999999999,"gpPct":29.75684336074317,"txns":85,"customers":72},{"store":"161","name":"JEFFERSONVILLE, VT - (ACE)","city":"Jeffersonville","state":"VT","sales":2369.35,"plan":5439.02,"pctToPlan":43.56207552095782,"gp":1027.2371999999998,"gpPct":43.355232447717725,"txns":66,"customers":62},{"store":"103","name":"RUMFORD, ME - (ACE)","city":"Rumford","state":"ME","sales":2319.73,"plan":3395.57,"pctToPlan":68.31636514635245,"gp":934.5617,"gpPct":40.28752053040655,"txns":73,"customers":68},{"store":"223","name":"DUBLIN, PA - ACE","city":"Dublin","state":"PA","sales":2311.47,"plan":5627.14,"pctToPlan":41.07717241796009,"gp":1112.2567,"gpPct":48.11901949841443,"txns":59,"customers":52},{"store":"55","name":"NEWPORT, NH - ACE","city":"Newport","state":"NH","sales":2213.27,"plan":3657.26,"pctToPlan":60.517163122118745,"gp":894.2662,"gpPct":40.40474953349569,"txns":57,"customers":53},{"store":"44","name":"WALPOLE, NH - ACE","city":"Walpole","state":"NH","sales":2200.74,"plan":4832.07,"pctToPlan":45.54445610266407,"gp":990.0569999999998,"gpPct":44.98745876387033,"txns":56,"customers":51},{"store":"151","name":"MIDDLEBORO, MA - ACE","city":"Middleboro","state":"MA","sales":2157.88,"plan":5862.23,"pctToPlan":36.80988292851015,"gp":1051.5299,"gpPct":48.7297671788978,"txns":77,"customers":70},{"store":"177","name":"RICHFIELD SPRINGS, NY - ACE","city":"Richfield Springs","state":"NY","sales":2113.8,"plan":3596.3,"pctToPlan":58.77707643967411,"gp":900.9543000000001,"gpPct":42.62249503264264,"txns":56,"customers":47},{"store":"195","name":"ALEXANDRIA, VA - (ACE)","city":"Alexandria","state":"VA","sales":1986.83,"plan":6613.31,"pctToPlan":30.042898336838885,"gp":834.7736,"gpPct":42.01535108690729,"txns":64,"customers":58},{"store":"79","name":"FAIR HAVEN, VT - (IND)","city":"Fair Haven","state":"VT","sales":1971.14,"plan":5226.91,"pctToPlan":37.711382059381165,"gp":877.4366,"gpPct":44.514169465385514,"txns":90,"customers":78},{"store":"1","name":"FITCHBURG,  MA - IND","city":"Fitchburg","state":"MA","sales":1893.68,"plan":3925.31,"pctToPlan":48.24281394335734,"gp":869.1853000000001,"gpPct":45.89927020404715,"txns":70,"customers":65},{"store":"80","name":"ALLENSTOWN, NH - ACE","city":"Allenstown","state":"NH","sales":1876.54,"plan":4368.45,"pctToPlan":42.9566551065023,"gp":917.5562,"gpPct":48.89617061187078,"txns":59,"customers":56},{"store":"89","name":"WAREHAM, MA - ACE","city":"Wareham","state":"MA","sales":1835.92,"plan":4114.04,"pctToPlan":44.62572070276419,"gp":764.9497000000001,"gpPct":41.66574251601378,"txns":58,"customers":51},{"store":"199","name":"RICHBORO, PA - IND","city":"Richboro","state":"PA","sales":1791.48,"plan":4424.23,"pctToPlan":40.49246987611404,"gp":866.6955,"gpPct":48.378742715520126,"txns":82,"customers":80},{"store":"140","name":"WEST CARTHAGE, NY - (IND)","city":"Carthage","state":"NY","sales":1777.25,"plan":5188.01,"pctToPlan":34.25687305922695,"gp":806.6883,"gpPct":45.38969193979463,"txns":66,"customers":62},{"store":"155","name":"SANDWICH, MA - (IND)","city":"Sandwich","state":"MA","sales":1769.38,"plan":3354.86,"pctToPlan":52.740799914154394,"gp":799.2636000000001,"gpPct":45.17195853914931,"txns":64,"customers":57},{"store":"181","name":"PLYMOUTH, MA - (ACE)","city":"Plymouth","state":"MA","sales":1748.73,"plan":3670.28,"pctToPlan":47.64568370805497,"gp":848.7462,"gpPct":48.5350054039217,"txns":62,"customers":57},{"store":"17","name":"TURNERS FALLS, MA - (IND)","city":"Turners Falls","state":"MA","sales":1745.34,"plan":3832.77,"pctToPlan":45.53730069897228,"gp":861.4633999999999,"gpPct":49.35791307137864,"txns":87,"customers":81},{"store":"97","name":"LISBON FALLS, ME - ACE","city":"Lisbon Falls","state":"ME","sales":1745.08,"plan":4816.62,"pctToPlan":36.23038562311331,"gp":826.1786,"gpPct":47.343308043184265,"txns":77,"customers":63},{"store":"106","name":"LINCOLN, ME - (ACE)","city":"Lincoln","state":"ME","sales":1739.45,"plan":7227.36,"pctToPlan":24.067571007947578,"gp":682.0184000000002,"gpPct":39.20885337319268,"txns":61,"customers":48},{"store":"64","name":"AUGUSTA, ME - (ACE)","city":"Augusta","state":"ME","sales":1703.72,"plan":3214.97,"pctToPlan":52.99334052883853,"gp":903.2945,"gpPct":53.01895264480079,"txns":54,"customers":51},{"store":"56","name":"OLD TOWN, ME - ACE","city":"Old Town","state":"ME","sales":1671.27,"plan":6130.28,"pctToPlan":27.262539394611668,"gp":821.1992,"gpPct":49.136237711441,"txns":73,"customers":66},{"store":"62","name":"HARDWICK, VT - (ACE)","city":"Hardwick","state":"VT","sales":1621.62,"plan":3356.48,"pctToPlan":48.31311373820192,"gp":634.0681999999999,"gpPct":39.100911434244765,"txns":42,"customers":39},{"store":"100","name":"MILTON, VT - (IND)","city":"Milton","state":"VT","sales":1619.74,"plan":3199.2,"pctToPlan":50.62953238309578,"gp":599.9845,"gpPct":37.04202526331387,"txns":60,"customers":54},{"store":"84","name":"TICONDEROGA, NY- ACE","city":"Ticonderoga","state":"NY","sales":1603.8,"plan":4211.91,"pctToPlan":38.07773670377572,"gp":623.2691,"gpPct":38.86202144905849,"txns":55,"customers":47},{"store":"168","name":"HILLSBORO, NH - (IND)","city":"Hillsboro","state":"NH","sales":1508.27,"plan":3856.09,"pctToPlan":39.11397296224932,"gp":705.4497,"gpPct":46.77210976814496,"txns":62,"customers":57},{"store":"39","name":"WINDSOR, VT - (ACE)","city":"Windsor","state":"VT","sales":1370.8,"plan":3338.44,"pctToPlan":41.06109440337403,"gp":654.3974999999999,"gpPct":47.73836445871024,"txns":63,"customers":59},{"store":"194","name":"MONROE, CT - (ACE)","city":"Monroe","state":"CT","sales":1328.55,"plan":3558.04,"pctToPlan":37.33937785972052,"gp":671.852,"gpPct":50.57032102668323,"txns":41,"customers":35},{"store":"163","name":"WARNER, NH - (IND)","city":"Warner","state":"NH","sales":1304.91,"plan":3794.88,"pctToPlan":34.38606754363774,"gp":593.9899,"gpPct":45.51960671617199,"txns":54,"customers":50},{"store":"196","name":"BLUE BELL, PA - ACE","city":"Blue Bell","state":"PA","sales":1292.52,"plan":3427.34,"pctToPlan":37.712044909463316,"gp":609.9816,"gpPct":47.193203973632905,"txns":61,"customers":59},{"store":"76","name":"SWANTON, VT - (IND)","city":"Swanton","state":"VT","sales":1283.96,"plan":3258.36,"pctToPlan":39.40509949790692,"gp":544.494,"gpPct":42.40739586903019,"txns":40,"customers":35},{"store":"176","name":"NEWMARKET, NH - (ACE)","city":"Newmarket","state":"NH","sales":1281.81,"plan":5074.34,"pctToPlan":25.260625027097117,"gp":530.9169999999999,"gpPct":41.41932111623407,"txns":63,"customers":60},{"store":"228","name":"NEW BRITAIN, PA - ACE","city":"NEW BRITAIN","state":"PA","sales":1269.76,"plan":5477.2,"pctToPlan":23.182648068356094,"gp":577.3474,"gpPct":45.469017767137096,"txns":43,"customers":37},{"store":"91","name":"MANCHESTER, VT - (ACE)","city":"Manchester Center","state":"VT","sales":1220.1,"plan":5128.53,"pctToPlan":23.79044287544384,"gp":503.2413999999999,"gpPct":41.245914269322185,"txns":41,"customers":37},{"store":"107","name":"NORTH WINDHAM, ME - ACE","city":"Windham","state":"ME","sales":1187.9,"plan":3452.49,"pctToPlan":34.40705114279839,"gp":625.7905000000001,"gpPct":52.68040239077364,"txns":47,"customers":39},{"store":"75","name":"ELIZABETHTOWN, NY - ACE","city":"Elizabethtown","state":"NY","sales":1163.11,"plan":3465.31,"pctToPlan":33.56438529309066,"gp":442.69309999999984,"gpPct":38.061155006835115,"txns":71,"customers":62},{"store":"92","name":"BERLIN, NH - (IND)","city":"Berlin","state":"NH","sales":1138.48,"plan":2548.07,"pctToPlan":44.68009120628554,"gp":405.97580000000005,"gpPct":35.659458225001764,"txns":51,"customers":45},{"store":"70","name":"PUTNAM, CT - (ACE)","city":"Putnam","state":"CT","sales":1136.13,"plan":3734.5,"pctToPlan":30.42254652563931,"gp":564.4948,"gpPct":49.68575779180199,"txns":53,"customers":48},{"store":"148","name":"AYER, MA - (IND)","city":"Ayer","state":"MA","sales":1058.48,"plan":3943.84,"pctToPlan":26.838816990547283,"gp":453.5779,"gpPct":42.851815811352125,"txns":57,"customers":52},{"store":"120","name":"PLATTSBURGH, NY - (IND)","city":"Plattsburgh","state":"NY","sales":998.4,"plan":4258.97,"pctToPlan":23.442287689276984,"gp":511.9147,"gpPct":51.27350761217949,"txns":60,"customers":53},{"store":"193","name":"SUDBURY, MA - (IND)","city":"Sudbury","state":"MA","sales":986.58,"plan":3086.77,"pctToPlan":31.96156500160362,"gp":453.14660000000003,"gpPct":45.931054754809544,"txns":33,"customers":29},{"store":"69","name":"LUNENBURG, MA - (IND)","city":"Lunenburg","state":"MA","sales":920.81,"plan":2346.31,"pctToPlan":39.2450272981831,"gp":183.7258999999999,"gpPct":19.95263952389743,"txns":49,"customers":45},{"store":"33","name":"GREAT BARRINGTON, MA - (ACE)","city":"Great Barrington","state":"MA","sales":876.06,"plan":3268.42,"pctToPlan":26.803776748398306,"gp":424.05139999999994,"gpPct":48.404378695523135,"txns":38,"customers":35},{"store":"60","name":"GOUVERNEUR, NY - (IND)","city":"Gouverneur","state":"NY","sales":846.87,"plan":2384.24,"pctToPlan":35.51949468174345,"gp":354.044,"gpPct":41.806180405493166,"txns":39,"customers":36},{"store":"101","name":"WINCHESTER, NH - (ACE)","city":"Winchester","state":"NH","sales":815.71,"plan":2896.93,"pctToPlan":28.157739399985505,"gp":380.66620000000006,"gpPct":46.66685464196835,"txns":42,"customers":40},{"store":"40","name":"BREWER, ME - (ACE)","city":"Brewer","state":"ME","sales":628.67,"plan":3418.04,"pctToPlan":18.392704590935153,"gp":333.3035,"gpPct":53.01724275056866,"txns":36,"customers":32}],"topProducts":[{"product":"MIDWEST NUTS & BOLTS","productCode":25,"sales":8614.61},{"product":"REGAL,SLCT.EGSHL,PSTL 1G#5491X","productCode":500808,"sales":6528.58},{"product":"33-1/2X61H REP DH","productCode":1170930198002447,"sales":4039.1},{"product":"REGAL,SLCT.MATTE,PSTL.1G#5481X","productCode":500816,"sales":3255.56},{"product":"EM5000XK3AN/2 - GENERATOR","productCode":384232,"sales":2600},{"product":".75CU.FT MG GARDEN SOIL","productCode":937435,"sales":2406.87},{"product":"SCOTTS  4 STEP 15M","productCode":15000,"sales":2319.92},{"product":"FRESHSTRT,SUPRIOR,WHT.1G#04600","productCode":500833,"sales":2024.56},{"product":"BR 800X BLOWER","productCode":194586,"sales":1949.97},{"product":"LM2135SP 21\" SELECT CUT SP LAW","productCode":736741,"sales":1947},{"product":"2CUFT/50QT MG POTTING MIX","productCode":102836,"sales":1937.5},{"product":"PRO-880 ULTRA WALLPRP ADH 5G","productCode":634019,"sales":1919.76},{"product":"BROWN SCOTTS MULCH","productCode":133666,"sales":1799.38},{"product":"GEN SA-E-325 LP INDIGO","productCode":791939,"sales":1798},{"product":"BR600Z BLOWER, BACKPACK","productCode":410926,"sales":1649.97},{"product":"CEILING,WTRBORN,WHT.1G #N50809","productCode":122385,"sales":1623.72},{"product":"TRUFUEL 50:1 2CYCLE 110 OZ","productCode":705228,"sales":1534.47},{"product":"REGAL,SLCT.S.GLS,PSTL.1G#5511X","productCode":500800,"sales":1426.33},{"product":"WOODLUXE WB D/S STN SLD B4 GL","productCode":792745,"sales":1424.81},{"product":"NAILER STRG FINISH 16GA","productCode":416000,"sales":1406.97},{"product":"CEILING,WTRBORN,WHT.5G #050809","productCode":122386,"sales":1349.95},{"product":"PRIMER-SEALER,B-I-N,GAL.#00901","productCode":265116,"sales":1301.86},{"product":"SUPER HIDE INT SG WH 5G","productCode":849354,"sales":1247.94},{"product":"AURA,INT.MATTE,PSTL,1G  #05221","productCode":122338,"sales":1247.87},{"product":"STEP 1 CRAB & FERT15000","productCode":134239,"sales":1199.88},{"product":"LWN MWR GS STL 163CC 21\"","productCode":846315,"sales":1197},{"product":"AURA,BATH&SPA,MATTE,B1,G#05321","productCode":122482,"sales":1151.88},{"product":"PROPANE, TANK, EX 20LB","productCode":105,"sales":1096.59},{"product":"BLACK SCOTTS MULCH","productCode":114960,"sales":1082.74},{"product":"KM 131 R LOOP HNDL KOMBISYSTEM","productCode":130744,"sales":1079.98},{"product":"CRYSTALS,SOLAR SALT, 40LB","productCode":604998,"sales":1061.08},{"product":"GEN E-330 NG BLK","productCode":763520,"sales":1049},{"product":"BEN,INT.EGSHL,PASTEL,1G #N6261","productCode":122413,"sales":1043.82},{"product":"PREMIUM TOP SOIL .75CF","productCode":225006,"sales":1017.96},{"product":"ULTRSPC-500,EGSH.PSTL.5G#5381","productCode":140852,"sales":935.96},{"product":"COMPOST,LBSTR,QUODDY 1CFT-","productCode":116766,"sales":917.34},{"product":"RAISED BED MIX, CASTINE 2CUFT","productCode":193991,"sales":913.6},{"product":"REGSLCT.EXT.LLST.PSTL.1G#N4011","productCode":311161,"sales":879.89},{"product":"SALT,F/SOFTENR,BRGHT SOFT,40LB","productCode":104697,"sales":856.14},{"product":"SEED,50# CONSERVATION #0171063","productCode":118759,"sales":849.95},{"product":"PROPANE,TANK, 20LB W/OPD VALVE","productCode":161927,"sales":839.88},{"product":"ACQUISITION ITEMS","productCode":963208,"sales":837.96},{"product":"WILD BIRD FOOD 20# ACE","productCode":781035,"sales":829.96},{"product":"SUPERHIDE  FLAT-CLNG WH 5G","productCode":256150,"sales":829.95},{"product":"MURESCO,CEILING,WHT.1G  #25801","productCode":110263,"sales":824.08},{"product":"1.5CF MG ORG BED/GARDEN SOIL","productCode":765126,"sales":810},{"product":"SLATE 30\" LP GRIDDLE BLK","productCode":791909,"sales":799},{"product":"GEN E-315 LP BLK","productCode":747195,"sales":799},{"product":"BA4200T 56V G3 3P 7.5AH","productCode":726313,"sales":798},{"product":"CONCRETE,MIX,80-LB.    #110180","productCode":219022,"sales":793.82},{"product":"MS 261-Z CHAINSAW,50CM/20\"","productCode":801380,"sales":779.99},{"product":"WTW5057LW WHL TL WASHER CONVRT","productCode":759680,"sales":777.95},{"product":"BR 800 C-E MAGNUM BLOWER","productCode":194535,"sales":749.99},{"product":"WHEELBARROW 6CF STL 2WHL","productCode":721102,"sales":749.95},{"product":"WOODLUXE WB D/S STN SLD B3 GL","productCode":792743,"sales":749.9},{"product":"POKEMON - PERFECT ORDER BOOST","productCode":963314,"sales":743.07},{"product":"ULTRSPC-500,EGSH.PSTL.1G#5381","productCode":140851,"sales":741.86},{"product":"REGAL,SLCT.PEARL,PSTL.1G#5501X","productCode":128578,"sales":739.9},{"product":"REGAL,SLCT.PEARL,WHT.1G #55001","productCode":128575,"sales":739.9},{"product":"BR700Z BACKPACK BLOWER","productCode":411628,"sales":729.99},{"product":"ACE WEED&FEED 15M","productCode":726473,"sales":729.89},{"product":"WOODLUXE WB D/S STN SLD B4 5G","productCode":792746,"sales":719.98},{"product":"SCOTTS 4 STEP 5M","productCode":5000,"sales":719.94},{"product":"40LB PELLETIZED LIME","productCode":101600,"sales":719.28},{"product":"DUMP SKU 901","productCode":901,"sales":718.75},{"product":"BEN,INT.EGSHL,MEDIUM,1G #N6262","productCode":122415,"sales":695.88},{"product":"1.5CF SCOTTS LAWN SOIL","productCode":944662,"sales":682.8},{"product":"GRASS SEED, THICK 'R LAWN 40LB","productCode":193502,"sales":679.9},{"product":"PAPR YARD BAG ACE 30G PK5","productCode":779028,"sales":679},{"product":"WOODLUXE WB D/S STN SLD B2 GL","productCode":792741,"sales":674.91},{"product":"SRM-225I -21.2CC STRT EZ START","productCode":760983,"sales":659.98},{"product":"ADVANCE,INT.SATIN,PSTL.1G#7921","productCode":128508,"sales":655.92},{"product":"TRD CRD ILSTRTN","productCode":989576,"sales":649.87},{"product":"7/16X4X8 OSB SHEATHING","productCode":364252,"sales":649.5},{"product":"MOORGLO,S.GLS.BRL.WH.1G#W09601","productCode":133610,"sales":639.92},{"product":"WOODLUXE WB STAIN ST TINT GAL","productCode":792732,"sales":639.9},{"product":"SALT,F/SOFTENR,IRON FIGHT,40LB","productCode":217794,"sales":639.89},{"product":"BEN INT LATEX MATTE PASTE GL","productCode":589137,"sales":637.89},{"product":"BLACK MULCH/SCOOP","productCode":743742,"sales":630},{"product":"BA2800T 56V G3 2P 5.0AH","productCode":721085,"sales":628},{"product":"21-3/4X61H REP DH","productCode":1170930198002448,"sales":610},{"product":"EZ STRAW MULCH 2.5CF","productCode":201926,"sales":607.72},{"product":"S-SPIRIT EP-425NG BLK","productCode":825458,"sales":600.98},{"product":"WOODLUXE WB D/S STN SLD B1 GL","productCode":792739,"sales":599.92},{"product":"PELLET,GREEN SUPREME,BLEND40LB","productCode":129991,"sales":591.26},{"product":"CONCRETE,MIX,60-LB     #110160","productCode":190302,"sales":583.27},{"product":"EC WEED PREVENTR 13.75LB","productCode":361584,"sales":574.91},{"product":"REGAL,SLCT.EGSHL,PSTL.QT#5491X","productCode":500807,"sales":560.83},{"product":"BEN,INT.EGSHL,PASTEL,5G #N6261","productCode":122478,"sales":559.98},{"product":"BEN INT LATEX MATTE PASTEL 5G","productCode":589146,"sales":559.98},{"product":"REGSLCT.EXT.LLST.WH.1G #N40101","productCode":311159,"sales":559.93},{"product":"5/8 X 100' ZERO-G LIGHTWEIGHT","productCode":189542,"sales":559.92},{"product":"REGAL,SLCT.FLAT,PSTL.1G #5471X","productCode":500824,"sales":559.92},{"product":"1/2X6X16 SPRUCE CLAPBOARD","productCode":364002,"sales":559.2},{"product":"GRIDDLE 4BRNR BLKSTONE W HOOD","productCode":800000,"sales":549.99},{"product":"HEATER,WATER,ELEC.50-G#6EM50-D","productCode":139874,"sales":549.99},{"product":"RAPID GRASS, SUNSHADE 16LB","productCode":385678,"sales":549.95},{"product":"GRASS SEED, SUN/SHADE 20LB","productCode":130604,"sales":549.95},{"product":"PROMIX BX 3.8CF","productCode":602170,"sales":549.9},{"product":"MS 271 20IN CHAINSAW","productCode":137212,"sales":539.99}],"notReporting":[{"store":"233","name":"ITHACA, NY - DOWNTOWN - (ACE)","city":"Ithaca","state":"NY","plan":32271.17},{"store":"234","name":"ITHACA, NY - TRIPHAMMER - (ACE)","city":"Ithaca","state":"NY","plan":22623.03},{"store":"108","name":"FARMINGTON, ME - ACE","city":"Farmington","state":"ME","plan":7183.71}],"asOf":"2026-04-23T16:15:09.673000","asOfET":"Apr 23, 2026, 12:15 PM","refreshedAt":"2026-04-23T16:26:21.065Z","storeCount":133,"prediction":{"updatedAt":"2026-04-23T16:26:21.071Z","updatedAtET":"Apr 23, 2026, 12:26 PM","dateET":"2026-04-23","dow":4,"season":"spring","source":"yoda","current":{"ts":"2026-04-23T16:26:21.071Z","tsET":"Apr 23, 2026, 12:26 PM","dateET":"2026-04-23","hourET":12,"minuteET":26,"dow":4,"sales":452848.63999999984,"plan":1073381.2100000002,"pctToPlan":42.188985216165634,"gp":190478.56849999976,"gpPct":42.06230331176435,"txns":12518,"customers":11496,"storeCount":133,"asOf":"2026-04-23T16:15:09.673000","asOfET":"Apr 23, 2026, 12:15 PM"},"prediction":{"available":true,"method":"blended (w=0.54 shape + 0.46 level)","confidence":"medium","projectedEOD":1007822.9387489818,"projectedPctToPlan":93.8923589643405,"projectedVariance":-65558.27125101839,"band":{"low":849573.9876735709,"high":1166071.8898243925},"pctOfDayElapsed":0.47174666666666665,"level_EOD":1063578.63123636,"shape_EOD":959940.3069444048,"blendWeight":0.537983346105744,"factors":{"plan":1073381.2100000002,"recencyFactor":0.9393,"dowPlanRatio":1.0549,"holidayKey":null,"holidayMult":1,"weatherKey":"normal","weatherMult":1,"weatherSummary":"concord-nh: 58F Sunny | worcester-ma: 60F Sunny | burlington-vt: 56F Sunny | portland-me: 51F Chance Rain Showers then Mostly Sunny | albany-ny: 65F Sunny | scranton-pa: 70F Patchy Fog then Sunny"},"shapeDetail":{"basePaceFromCurve":0.47174666666666665,"observedPaceCount":1,"blendedPaceAtNow":0.47174666666666665,"historyDays":1,"avgHistoricalEOD":1053994.8399999996},"note":"Plan-anchored forecast. Early in the day we trust plan × factors; later we trust the pace curve.","offlineEstimate":{"estimatedCurrent":21681.005053333334,"estimatedEOD":45959,"paceUsed":0.47174666666666665,"perStore":[{"storeCd":"233","name":"ITHACA, NY - DOWNTOWN","dowEOD":30687,"estimatedCurrent":14476.489959999999,"estimatedEOD":30687,"stdev":0.3949},{"storeCd":"234","name":"ITHACA, NY - TRIPHAMMER","dowEOD":15272,"estimatedCurrent":7204.515093333333,"estimatedEOD":15272,"stdev":0.1435}],"source":"RPT_SCORECARD_BY_DAY, 12 weeks (Jan 25 - Apr 17 2026) with 2x weight on last 28 days"},"combinedProjectedEOD":1053781.9387489818,"combinedCurrentSales":474529.6450533332,"footnote":"Company total excludes 2 stores not on live feed (233, 234). Estimated contribution: $21,681 so far, +$45,959 to EOD."},"offlineStoresVersion":2,"baselineVersion":10,"weatherRaw":{"mult":1,"key":"normal","season":"spring","summary":"concord-nh: 58F Sunny | worcester-ma: 60F Sunny | burlington-vt: 56F Sunny | portland-me: 51F Chance Rain Showers then Mostly Sunny | albany-ny: 65F Sunny | scranton-pa: 70F Patchy Fog then Sunny","tagWeights":{"normal":0.64,"rain_gt_0_5in":0.152,"perfect_65_80F_dry":0.208},"forecasts":[{"station":"concord-nh","weight":0.144,"temp":58,"unit":"F","short":"Sunny","detailed":"Sunny, with a high near 58. Northwest wind 0 to 15 mph, with gusts as high as 35 mph."},{"station":"worcester-ma","weight":0.272,"temp":60,"unit":"F","short":"Sunny","detailed":"Sunny, with a high near 60. Northwest wind 6 to 14 mph, with gusts as high as 29 mph."},{"station":"burlington-vt","weight":0.224,"temp":56,"unit":"F","short":"Sunny","detailed":"Sunny, with a high near 56. North wind around 15 mph, with gusts as high as 28 mph."},{"station":"portland-me","weight":0.152,"temp":51,"unit":"F","short":"Chance Rain Showers then Mostly Sunny","detailed":"A chance of rain showers before 8am. Mostly sunny, with a high near 51. Northwest wind 5 to 15 mph, with gusts as high as 25 mph. Chance of precipitation is 30%. New rainfall amounts less than a tenth of an inch possible."},{"station":"albany-ny","weight":0.12,"temp":65,"unit":"F","short":"Sunny","detailed":"Sunny, with a high near 65. North wind 10 to 15 mph."},{"station":"scranton-pa","weight":0.088,"temp":70,"unit":"F","short":"Patchy Fog then Sunny","detailed":"Patchy fog before 9am. Sunny, with a high near 70. Northwest wind 3 to 12 mph, with gusts as high as 23 mph."}]}},"snapshotAt":"2026-04-23T16:26:22.686Z"}